{"fetched_at":1762191620.8333566,"ctype":"application/json; charset=utf-8","body":{"user":{"user_uid":"0ryvtzl0l","nid":null,"gnid":null,"name":"lophenix","level":274,"exp":359,"trophy":43411,"highestTrophy":43411,"iconId":404016,"frameId":1000008,"createdAt":"2022-12-18T14:26:40.218Z","updatedAt":"2025-11-03T16:42:36.000Z","clan_uid":"ib0dy3s1n9zl","clan_name":"FireStarsZ","clan_short_name":"FIRE","clan_iconId":0,"growthExp":164,"growthLevel":12,"fortuneExp":6601,"fortuneLevel":10,"fame":23170},"compliment":1529,"trophy":43411,"rankDetails":[{"user_uid":"0ryvtzl0l","seasonId":10,"modeId":4,"rankPoint":0,"maxRankPoint":0,"tier":"UNRANKED","tierScore":0,"maxTier":"UNRANKED","maxTierScore":0,"remainPlacement":5,"totalPlacement":6,"gameCount":1},{"user_uid":"0ryvtzl0l","seasonId":11,"modeId":4,"rankPoint":0,"maxRankPoint":0,"tier":"UNRANKED","tierScore":0,"maxTier":"UNRANKED","maxTierScore":0,"remainPlacement":1,"totalPlacement":6,"gameCount":5},{"user_uid":"0ryvtzl0l","seasonId":12,"modeId":4,"rankPoint":932,"maxRankPoint":1165,"tier":"PLATINUM_3","tierScore":32,"maxTier":"PLATINUM_1","maxTierScore":65,"remainPlacement":0,"totalPlacement":6,"gameCount":92},{"user_uid":"0ryvtzl0l","seasonId":13,"modeId":4,"rankPoint":1021,"maxRankPoint":1066,"tier":"PLATINUM_2","tierScore":21,"maxTier":"PLATINUM_2","maxTierScore":66,"remainPlacement":0,"totalPlacement":6,"gameCount":68},{"user_uid":"0ryvtzl0l","seasonId":14,"modeId":4,"rankPoint":635,"maxRankPoint":726,"tier":"GOLD_3","tierScore":35,"maxTier":"GOLD_2","maxTierScore":26,"remainPlacement":0,"totalPlacement":6,"gameCount":57},{"user_uid":"0ryvtzl0l","seasonId":15,"modeId":3,"rankPoint":634,"maxRankPoint":671,"tier":"GOLD_3","tierScore":34,"maxTier":"GOLD_3","maxTierScore":71,"remainPlacement":0,"totalPlacement":6,"gameCount":16},{"user_uid":"0ryvtzl0l","seasonId":15,"modeId":4,"rankPoint":645,"maxRankPoint":733,"tier":"GOLD_3","tierScore":45,"maxTier":"GOLD_2","maxTierScore":33,"remainPlacement":0,"totalPlacement":6,"gameCount":24},{"user_uid":"0ryvtzl0l","seasonId":16,"modeId":3,"rankPoint":636,"maxRankPoint":636,"tier":"GOLD_3","tierScore":36,"maxTier":"GOLD_3","maxTierScore":36,"remainPlacement":0,"totalPlacement":6,"gameCount":8},{"user_uid":"0ryvtzl0l","seasonId":16,"modeId":4,"rankPoint":849,"maxRankPoint":893,"tier":"GOLD_1","tierScore":49,"maxTier":"GOLD_1","maxTierScore":93,"remainPlacement":0,"totalPlacement":6,"gameCount":24},{"user_uid":"0ryvtzl0l","seasonId":17,"modeId":3,"rankPoint":723,"maxRankPoint":723,"tier":"GOLD_2","tierScore":23,"maxTier":"GOLD_2","maxTierScore":23,"remainPlacement":0,"totalPlacement":6,"gameCount":13},{"user_uid":"0ryvtzl0l","seasonId":17,"modeId":4,"rankPoint":715,"maxRankPoint":715,"tier":"GOLD_2","tierScore":15,"maxTier":"GOLD_2","maxTierScore":15,"remainPlacement":0,"totalPlacement":6,"gameCount":16},{"user_uid":"0ryvtzl0l","seasonId":18,"modeId":3,"rankPoint":0,"maxRankPoint":0,"tier":"UNRANKED","tierScore":0,"maxTier":"UNRANKED","maxTierScore":0,"remainPlacement":6,"totalPlacement":6,"gameCount":0},{"user_uid":"0ryvtzl0l","seasonId":18,"modeId":4,"rankPoint":868,"maxRankPoint":992,"tier":"GOLD_1","tierScore":68,"maxTier":"PLATINUM_3","maxTierScore":92,"remainPlacement":0,"totalPlacement":6,"gameCount":15},{"user_uid":"0ryvtzl0l","seasonId":19,"modeId":4,"rankPoint":761,"maxRankPoint":761,"tier":"GOLD_2","tierScore":61,"maxTier":"GOLD_2","maxTierScore":61,"remainPlacement":0,"totalPlacement":6,"gameCount":7},{"user_uid":"0ryvtzl0l","seasonId":20,"modeId":4,"rankPoint":821,"maxRankPoint":858,"tier":"GOLD_1","tierScore":21,"maxTier":"GOLD_1","maxTierScore":58,"remainPlacement":0,"totalPlacement":6,"gameCount":12},{"user_uid":"0ryvtzl0l","seasonId":21,"modeId":4,"rankPoint":0,"maxRankPoint":0,"tier":"UNRANKED","tierScore":0,"maxTier":"UNRANKED","maxTierScore":0,"remainPlacement":4,"totalPlacement":6,"gameCount":2},{"user_uid":"0ryvtzl0l","seasonId":22,"modeId":4,"rankPoint":771,"maxRankPoint":771,"tier":"GOLD_2","tierScore":71,"maxTier":"GOLD_2","maxTierScore":71,"remainPlacement":0,"totalPlacement":6,"gameCount":15},{"user_uid":"0ryvtzl0l","seasonId":23,"modeId":4,"rankPoint":1058,"maxRankPoint":1058,"tier":"PLATINUM_2","tierScore":58,"maxTier":"PLATINUM_2","maxTierScore":58,"remainPlacement":0,"totalPlacement":6,"gameCount":89},{"user_uid":"0ryvtzl0l","seasonId":24,"modeId":4,"rankPoint":673,"maxRankPoint":673,"tier":"GOLD_3","tierScore":73,"maxTier":"GOLD_3","maxTierScore":73,"remainPlacement":0,"totalPlacement":6,"gameCount":7},{"user_uid":"0ryvtzl0l","seasonId":25,"modeId":4,"rankPoint":900,"maxRankPoint":900,"tier":"PLATINUM_3","tierScore":0,"maxTier":"PLATINUM_3","maxTierScore":0,"remainPlacement":0,"totalPlacement":6,"gameCount":50},{"user_uid":"0ryvtzl0l","seasonId":26,"modeId":4,"rankPoint":849,"maxRankPoint":953,"tier":"GOLD_1","tierScore":49,"maxTier":"PLATINUM_3","maxTierScore":53,"remainPlacement":0,"totalPlacement":6,"gameCount":138},{"user_uid":"0ryvtzl0l","seasonId":27,"modeId":4,"rankPoint":809,"maxRankPoint":862,"tier":"GOLD_1","tierScore":9,"maxTier":"GOLD_1","maxTierScore":62,"remainPlacement":0,"totalPlacement":6,"gameCount":75},{"user_uid":"0ryvtzl0l","seasonId":28,"modeId":4,"rankPoint":921,"maxRankPoint":921,"tier":"PLATINUM_3","tierScore":21,"maxTier":"PLATINUM_3","maxTierScore":21,"remainPlacement":0,"totalPlacement":6,"gameCount":53},{"user_uid":"0ryvtzl0l","seasonId":29,"modeId":4,"rankPoint":909,"maxRankPoint":909,"tier":"PLATINUM_3","tierScore":9,"maxTier":"PLATINUM_3","maxTierScore":9,"remainPlacement":0,"totalPlacement":6,"gameCount":92},{"user_uid":"0ryvtzl0l","seasonId":30,"modeId":4,"rankPoint":912,"maxRankPoint":912,"tier":"PLATINUM_3","tierScore":12,"maxTier":"PLATINUM_3","maxTierScore":12,"remainPlacement":0,"totalPlacement":6,"gameCount":80},{"user_uid":"0ryvtzl0l","seasonId":31,"modeId":4,"rankPoint":1025,"maxRankPoint":1141,"tier":"PLATINUM_2","tierScore":25,"maxTier":"PLATINUM_1","maxTierScore":41,"remainPlacement":0,"totalPlacement":6,"gameCount":110},{"user_uid":"0ryvtzl0l","seasonId":32,"modeId":4,"rankPoint":909,"maxRankPoint":946,"tier":"PLATINUM_3","tierScore":9,"maxTier":"PLATINUM_3","maxTierScore":46,"remainPlacement":0,"totalPlacement":6,"gameCount":51},{"user_uid":"0ryvtzl0l","seasonId":33,"modeId":4,"rankPoint":904,"maxRankPoint":958,"tier":"PLATINUM_3","tierScore":4,"maxTier":"PLATINUM_3","maxTierScore":58,"remainPlacement":0,"totalPlacement":6,"gameCount":74},{"user_uid":"0ryvtzl0l","seasonId":34,"modeId":4,"rankPoint":924,"maxRankPoint":924,"tier":"PLATINUM_3","tierScore":24,"maxTier":"PLATINUM_3","maxTierScore":24,"remainPlacement":0,"totalPlacement":6,"gameCount":12},{"user_uid":"0ryvtzl0l","seasonId":35,"modeId":4,"rankPoint":915,"maxRankPoint":915,"tier":"PLATINUM_3","tierScore":15,"maxTier":"PLATINUM_3","maxTierScore":15,"remainPlacement":0,"totalPlacement":6,"gameCount":19},{"user_uid":"0ryvtzl0l","seasonId":36,"modeId":4,"rankPoint":937,"maxRankPoint":937,"tier":"PLATINUM_3","tierScore":37,"maxTier":"PLATINUM_3","maxTierScore":37,"remainPlacement":0,"totalPlacement":6,"gameCount":26},{"user_uid":"0ryvtzl0l","seasonId":37,"modeId":4,"rankPoint":904,"maxRankPoint":904,"tier":"PLATINUM_3","tierScore":4,"maxTier":"PLATINUM_3","maxTierScore":4,"remainPlacement":0,"totalPlacement":6,"gameCount":22},{"user_uid":"0ryvtzl0l","seasonId":38,"modeId":4,"rankPoint":1002,"maxRankPoint":1002,"tier":"PLATINUM_2","tierScore":2,"maxTier":"PLATINUM_2","maxTierScore":2,"remainPlacement":0,"totalPlacement":6,"gameCount":23},{"user_uid":"0ryvtzl0l","seasonId":39,"modeId":4,"rankPoint":843,"maxRankPoint":844,"tier":"GOLD_1","tierScore":43,"maxTier":"GOLD_1","maxTierScore":44,"remainPlacement":0,"totalPlacement":6,"gameCount":32},{"user_uid":"0ryvtzl0l","seasonId":40,"modeId":4,"rankPoint":741,"maxRankPoint":741,"tier":"GOLD_2","tierScore":41,"maxTier":"GOLD_2","maxTierScore":41,"remainPlacement":0,"totalPlacement":6,"gameCount":6},{"user_uid":"0ryvtzl0l","seasonId":41,"modeId":99,"rankPoint":784,"maxRankPoint":830,"tier":"GOLD_2","tierScore":84,"maxTier":"GOLD_1","maxTierScore":30,"remainPlacement":0,"totalPlacement":6,"gameCount":20},{"user_uid":"0ryvtzl0l","seasonId":42,"modeId":99,"rankPoint":0,"maxRankPoint":0,"tier":"UNRANKED","tierScore":0,"maxTier":"UNRANKED","maxTierScore":0,"remainPlacement":3,"totalPlacement":6,"gameCount":3},{"user_uid":"0ryvtzl0l","seasonId":43,"modeId":99,"rankPoint":668,"maxRankPoint":689,"tier":"GOLD_3","tierScore":68,"maxTier":"GOLD_3","maxTierScore":89,"remainPlacement":0,"totalPlacement":6,"gameCount":8},{"user_uid":"0ryvtzl0l","seasonId":44,"modeId":99,"rankPoint":644,"maxRankPoint":685,"tier":"GOLD_3","tierScore":44,"maxTier":"GOLD_3","maxTierScore":85,"remainPlacement":0,"totalPlacement":6,"gameCount":15}],"characters":{"characters":[{"characterId":101,"level":10,"trophy":1000,"highestTrophy":1000,"mastery":26,"unlockedAt":"2022-12-18T14:26:40.000Z","skinItemId":0,"revivalItemId":0,"knokoutItemId":0,"finalBlowItemId":0,"emoticonItemIds":[300008,300010,0,0]},{"characterId":102,"level":10,"trophy":1000,"highestTrophy":1000,"mastery":6464,"unlockedAt":"2022-12-24T08:21:39.000Z","skinItemId":210218,"revivalItemId":910004,"knokoutItemId":920033,"finalBlowItemId":930002,"emoticonItemIds":[300008,310208,310209,310220]},{"characterId":103,"level":10,"trophy":1000,"highestTrophy":1000,"mastery":450,"unlockedAt":"2023-03-14T16:40:07.000Z","skinItemId":210330,"revivalItemId":910004,"knokoutItemId":920033,"finalBlowItemId":930002,"emoticonItemIds":[300008,300010,0,0]},{"characterId":104,"level":10,"trophy":1000,"highestTrophy":1000,"mastery":1891,"unlockedAt":"2023-03-14T16:41:22.000Z","skinItemId":210422,"revivalItemId":910004,"knokoutItemId":920033,"finalBlowItemId":930002,"emoticonItemIds":[310404,310407,310408,310409]},{"characterId":105,"level":10,"trophy":794,"highestTrophy":794,"mastery":0,"unlockedAt":"2022-12-18T14:52:50.000Z","skinItemId":0,"revivalItemId":0,"knokoutItemId":0,"finalBlowItemId":0,"emoticonItemIds":[300008,300010,0,0]},{"characterId":106,"level":10,"trophy":1000,"highestTrophy":1000,"mastery":2194,"unlockedAt":"2023-03-14T16:40:24.000Z","skinItemId":210604,"revivalItemId":0,"knokoutItemId":0,"finalBlowItemId":0,"emoticonItemIds":[300008,300010,0,0]},{"characterId":108,"level":10,"trophy":1000,"highestTrophy":1000,"mastery":536,"unlockedAt":"2023-03-14T16:39:32.000Z","skinItemId":210804,"revivalItemId":0,"knokoutItemId":0,"finalBlowItemId":0,"emoticonItemIds":[300008,300010,0,0]},{"characterId":109,"level":10,"trophy":1000,"highestTrophy":1000,"mastery":1031,"unlockedAt":"2023-10-13T06:01:57.000Z","skinItemId":210903,"revivalItemId":0,"knokoutItemId":0,"finalBlowItemId":0,"emoticonItemIds":[300008,300010,0,0]},{"characterId":110,"level":10,"trophy":1000,"highestTrophy":1000,"mastery":606,"unlockedAt":"2023-03-14T16:44:14.000Z","skinItemId":211003,"revivalItemId":0,"knokoutItemId":0,"finalBlowItemId":0,"emoticonItemIds":[300008,300010,0,0]},{"characterId":111,"level":10,"trophy":1000,"highestTrophy":1000,"mastery":2141,"unlockedAt":"2022-12-18T15:00:19.000Z","skinItemId":211122,"revivalItemId":910004,"knokoutItemId":920033,"finalBlowItemId":930002,"emoticonItemIds":[311104,311107,311108,311109]},{"characterId":112,"level":10,"trophy":1000,"highestTrophy":1000,"mastery":1065,"unlockedAt":"2023-12-05T16:35:34.000Z","skinItemId":211215,"revivalItemId":910004,"knokoutItemId":920033,"finalBlowItemId":930002,"emoticonItemIds":[311207,311221,311208,311209]},{"characterId":113,"level":10,"trophy":1000,"highestTrophy":1000,"mastery":616,"unlockedAt":"2023-12-05T16:40:36.000Z","skinItemId":211321,"revivalItemId":910004,"knokoutItemId":920033,"finalBlowItemId":0,"emoticonItemIds":[311303,311308,311309,300005]},{"characterId":114,"level":10,"trophy":774,"highestTrophy":774,"mastery":0,"unlockedAt":"2023-03-14T16:46:26.000Z","skinItemId":0,"revivalItemId":0,"knokoutItemId":0,"finalBlowItemId":0,"emoticonItemIds":[300008,300010,0,0]},{"characterId":115,"level":10,"trophy":1000,"highestTrophy":1000,"mastery":1775,"unlockedAt":"2022-12-18T21:39:07.000Z","skinItemId":211502,"revivalItemId":910004,"knokoutItemId":920033,"finalBlowItemId":930002,"emoticonItemIds":[300008,300010,311504,311507]},{"characterId":116,"level":10,"trophy":1000,"highestTrophy":1000,"mastery":158,"unlockedAt":"2023-07-17T17:50:30.000Z","skinItemId":211602,"revivalItemId":910004,"knokoutItemId":920033,"finalBlowItemId":930002,"emoticonItemIds":[311604,311607,311608,311621]},{"characterId":117,"level":10,"trophy":1000,"highestTrophy":1000,"mastery":197,"unlockedAt":"2023-05-29T15:56:51.000Z","skinItemId":0,"revivalItemId":0,"knokoutItemId":0,"finalBlowItemId":0,"emoticonItemIds":[300008,300010,0,0]},{"characterId":118,"level":10,"trophy":1000,"highestTrophy":1000,"mastery":1722,"unlockedAt":"2023-12-08T16:07:32.000Z","skinItemId":211803,"revivalItemId":910004,"knokoutItemId":920033,"finalBlowItemId":930002,"emoticonItemIds":[311804,311807,311808,311809]},{"characterId":119,"level":10,"trophy":1000,"highestTrophy":1000,"mastery":10241,"unlockedAt":"2022-12-26T16:34:43.000Z","skinItemId":211916,"revivalItemId":910004,"knokoutItemId":920033,"finalBlowItemId":930002,"emoticonItemIds":[311904,311907,311908,311909]},{"characterId":120,"level":10,"trophy":1000,"highestTrophy":1000,"mastery":717,"unlockedAt":"2023-11-22T18:02:24.000Z","skinItemId":0,"revivalItemId":0,"knokoutItemId":0,"finalBlowItemId":0,"emoticonItemIds":[300008,300010,0,0]},{"characterId":121,"level":10,"trophy":1000,"highestTrophy":1000,"mastery":3328,"unlockedAt":"2023-11-22T18:02:43.000Z","skinItemId":212103,"revivalItemId":910004,"knokoutItemId":920033,"finalBlowItemId":930002,"emoticonItemIds":[312104,312107,312108,312109]},{"characterId":122,"level":10,"trophy":1000,"highestTrophy":1000,"mastery":10890,"unlockedAt":"2023-02-02T16:38:08.000Z","skinItemId":212220,"revivalItemId":910004,"knokoutItemId":920033,"finalBlowItemId":930002,"emoticonItemIds":[312204,312207,312208,312209]},{"characterId":123,"level":10,"trophy":1000,"highestTrophy":1000,"mastery":312,"unlockedAt":"2023-07-04T17:03:06.000Z","skinItemId":0,"revivalItemId":0,"knokoutItemId":0,"finalBlowItemId":0,"emoticonItemIds":[300008,300010,0,0]},{"characterId":124,"level":10,"trophy":742,"highestTrophy":742,"mastery":0,"unlockedAt":"2023-10-25T15:49:24.000Z","skinItemId":212415,"revivalItemId":910004,"knokoutItemId":920033,"finalBlowItemId":930002,"emoticonItemIds":[312404,312407,312408,312411]},{"characterId":125,"level":10,"trophy":1000,"highestTrophy":1000,"mastery":1706,"unlockedAt":"2023-12-07T16:52:32.000Z","skinItemId":212502,"revivalItemId":910004,"knokoutItemId":920033,"finalBlowItemId":930002,"emoticonItemIds":[312507,300010,312508,312509]},{"characterId":126,"level":10,"trophy":1000,"highestTrophy":1000,"mastery":435,"unlockedAt":"2023-03-14T16:44:56.000Z","skinItemId":0,"revivalItemId":0,"knokoutItemId":0,"finalBlowItemId":0,"emoticonItemIds":[300008,300010,0,0]},{"characterId":127,"level":10,"trophy":1000,"highestTrophy":1000,"mastery":1006,"unlockedAt":"2023-03-28T13:10:24.000Z","skinItemId":0,"revivalItemId":0,"knokoutItemId":0,"finalBlowItemId":0,"emoticonItemIds":[300008,300010,0,0]},{"characterId":128,"level":10,"trophy":1000,"highestTrophy":1000,"mastery":1582,"unlockedAt":"2023-03-14T16:41:48.000Z","skinItemId":212802,"revivalItemId":910004,"knokoutItemId":920033,"finalBlowItemId":930002,"emoticonItemIds":[312804,300010,312808,312809]},{"characterId":129,"level":10,"trophy":1000,"highestTrophy":1000,"mastery":146,"unlockedAt":"2023-10-29T11:32:17.000Z","skinItemId":0,"revivalItemId":0,"knokoutItemId":0,"finalBlowItemId":0,"emoticonItemIds":[300008,300010,0,0]},{"characterId":130,"level":10,"trophy":1000,"highestTrophy":1000,"mastery":111795,"unlockedAt":"2022-12-21T19:49:38.000Z","skinItemId":213003,"revivalItemId":910004,"knokoutItemId":920033,"finalBlowItemId":930002,"emoticonItemIds":[313007,313008,313009,313004]},{"characterId":131,"level":10,"trophy":1000,"highestTrophy":1000,"mastery":14219,"unlockedAt":"2023-04-21T08:09:19.000Z","skinItemId":0,"revivalItemId":910004,"knokoutItemId":920033,"finalBlowItemId":930002,"emoticonItemIds":[300008,313104,313107,313108]},{"characterId":132,"level":10,"trophy":1000,"highestTrophy":1000,"mastery":23662,"unlockedAt":"2023-02-14T16:23:29.000Z","skinItemId":213227,"revivalItemId":910004,"knokoutItemId":920033,"finalBlowItemId":930002,"emoticonItemIds":[313204,313207,313208,313209]},{"characterId":133,"level":10,"trophy":1000,"highestTrophy":1000,"mastery":4591,"unlockedAt":"2023-04-11T16:23:12.000Z","skinItemId":213302,"revivalItemId":910004,"knokoutItemId":920033,"finalBlowItemId":930002,"emoticonItemIds":[300008,313307,313308,313309]},{"characterId":134,"level":10,"trophy":1000,"highestTrophy":1000,"mastery":99,"unlockedAt":"2023-12-08T16:07:16.000Z","skinItemId":0,"revivalItemId":0,"knokoutItemId":0,"finalBlowItemId":0,"emoticonItemIds":[300008,300010,0,0]},{"characterId":135,"level":10,"trophy":1000,"highestTrophy":1000,"mastery":5880,"unlockedAt":"2023-08-01T16:05:19.000Z","skinItemId":0,"revivalItemId":910004,"knokoutItemId":920033,"finalBlowItemId":930002,"emoticonItemIds":[300010,313507,313508,313509]},{"characterId":136,"level":10,"trophy":1000,"highestTrophy":1000,"mastery":30957,"unlockedAt":"2023-09-26T17:18:26.000Z","skinItemId":213601,"revivalItemId":910004,"knokoutItemId":920033,"finalBlowItemId":930002,"emoticonItemIds":[300008,300010,313609,313608]},{"characterId":137,"level":10,"trophy":1000,"highestTrophy":1000,"mastery":19326,"unlockedAt":"2023-11-21T16:00:30.000Z","skinItemId":213702,"revivalItemId":910004,"knokoutItemId":920033,"finalBlowItemId":930002,"emoticonItemIds":[313704,313707,313708,313709]},{"characterId":138,"level":10,"trophy":1000,"highestTrophy":1000,"mastery":1848,"unlockedAt":"2023-12-08T15:55:27.000Z","skinItemId":0,"revivalItemId":910004,"knokoutItemId":920033,"finalBlowItemId":930002,"emoticonItemIds":[313804,313807,313808,313809]},{"characterId":139,"level":10,"trophy":798,"highestTrophy":798,"mastery":0,"unlockedAt":"2024-03-12T17:21:00.000Z","skinItemId":213902,"revivalItemId":910004,"knokoutItemId":920033,"finalBlowItemId":930002,"emoticonItemIds":[313904,313907,313908,313909]},{"characterId":140,"level":10,"trophy":1000,"highestTrophy":1000,"mastery":250,"unlockedAt":"2024-05-08T07:19:40.000Z","skinItemId":0,"revivalItemId":910004,"knokoutItemId":920033,"finalBlowItemId":930002,"emoticonItemIds":[314007,314008,314009,0]},{"characterId":141,"level":10,"trophy":1000,"highestTrophy":1000,"mastery":7044,"unlockedAt":"2024-07-16T15:36:08.000Z","skinItemId":0,"revivalItemId":910004,"knokoutItemId":920033,"finalBlowItemId":930002,"emoticonItemIds":[300008,300010,314107,314109]},{"characterId":142,"level":10,"trophy":1000,"highestTrophy":1000,"mastery":11941,"unlockedAt":"2024-09-10T08:40:16.000Z","skinItemId":214209,"revivalItemId":910004,"knokoutItemId":920033,"finalBlowItemId":930002,"emoticonItemIds":[300008,300010,314209,0]},{"characterId":143,"level":10,"trophy":701,"highestTrophy":701,"mastery":0,"unlockedAt":"2024-11-05T10:32:44.000Z","skinItemId":0,"revivalItemId":0,"knokoutItemId":0,"finalBlowItemId":0,"emoticonItemIds":[300008,300010,0,0]},{"characterId":144,"level":10,"trophy":602,"highestTrophy":602,"mastery":0,"unlockedAt":"2024-12-31T12:41:41.000Z","skinItemId":0,"revivalItemId":0,"knokoutItemId":0,"finalBlowItemId":0,"emoticonItemIds":[300008,300010,0,0]},{"characterId":145,"level":10,"trophy":1000,"highestTrophy":1000,"mastery":3521,"unlockedAt":"2025-02-25T17:45:55.000Z","skinItemId":0,"revivalItemId":910004,"knokoutItemId":920033,"finalBlowItemId":930002,"emoticonItemIds":[300008,300010,314509,0]},{"characterId":147,"level":10,"trophy":1000,"highestTrophy":1000,"mastery":7824,"unlockedAt":"2025-08-12T16:29:07.000Z","skinItemId":214731,"revivalItemId":910004,"knokoutItemId":920033,"finalBlowItemId":930002,"emoticonItemIds":[300008,300010,0,0]}]},"statsAll":{"competitive":[{"seasonId":10,"modeId":4,"characterId":132,"play":1,"win":0,"mvp":0},{"seasonId":11,"modeId":4,"characterId":122,"play":2,"win":2,"mvp":2},{"seasonId":11,"modeId":4,"characterId":130,"play":3,"win":2,"mvp":3},{"seasonId":12,"modeId":4,"characterId":122,"play":5,"win":3,"mvp":1},{"seasonId":12,"modeId":4,"characterId":130,"play":82,"win":41,"mvp":38},{"seasonId":12,"modeId":4,"characterId":132,"play":4,"win":0,"mvp":1},{"seasonId":13,"modeId":4,"characterId":106,"play":1,"win":1,"mvp":1},{"seasonId":13,"modeId":4,"characterId":111,"play":2,"win":1,"mvp":0},{"seasonId":13,"modeId":4,"characterId":119,"play":3,"win":2,"mvp":2},{"seasonId":13,"modeId":4,"characterId":130,"play":38,"win":14,"mvp":14},{"seasonId":13,"modeId":4,"characterId":132,"play":24,"win":16,"mvp":9},{"seasonId":14,"modeId":4,"characterId":119,"play":1,"win":0,"mvp":0},{"seasonId":14,"modeId":4,"characterId":130,"play":47,"win":21,"mvp":30},{"seasonId":14,"modeId":4,"characterId":132,"play":9,"win":6,"mvp":3},{"seasonId":15,"modeId":3,"characterId":128,"play":4,"win":1,"mvp":1},{"seasonId":15,"modeId":3,"characterId":130,"play":12,"win":8,"mvp":8},{"seasonId":15,"modeId":4,"characterId":128,"play":1,"win":0,"mvp":0},{"seasonId":15,"modeId":4,"characterId":130,"play":22,"win":10,"mvp":11},{"seasonId":15,"modeId":4,"characterId":132,"play":1,"win":1,"mvp":1},{"seasonId":16,"modeId":3,"characterId":130,"play":5,"win":4,"mvp":4},{"seasonId":16,"modeId":3,"characterId":131,"play":3,"win":1,"mvp":1},{"seasonId":16,"modeId":4,"characterId":130,"play":16,"win":9,"mvp":8},{"seasonId":16,"modeId":4,"characterId":131,"play":5,"win":4,"mvp":0},{"seasonId":16,"modeId":4,"characterId":132,"play":3,"win":2,"mvp":0},{"seasonId":17,"modeId":3,"characterId":128,"play":1,"win":1,"mvp":1},{"seasonId":17,"modeId":3,"characterId":130,"play":12,"win":8,"mvp":8},{"seasonId":17,"modeId":4,"characterId":130,"play":14,"win":9,"mvp":6},{"seasonId":17,"modeId":4,"characterId":131,"play":2,"win":0,"mvp":1},{"seasonId":18,"modeId":4,"characterId":119,"play":2,"win":2,"mvp":2},{"seasonId":18,"modeId":4,"characterId":130,"play":10,"win":6,"mvp":3},{"seasonId":18,"modeId":4,"characterId":131,"play":2,"win":1,"mvp":1},{"seasonId":18,"modeId":4,"characterId":132,"play":1,"win":0,"mvp":0},{"seasonId":19,"modeId":4,"characterId":119,"play":1,"win":0,"mvp":1},{"seasonId":19,"modeId":4,"characterId":130,"play":5,"win":4,"mvp":4},{"seasonId":19,"modeId":4,"characterId":132,"play":1,"win":1,"mvp":1},{"seasonId":20,"modeId":4,"characterId":119,"play":3,"win":2,"mvp":3},{"seasonId":20,"modeId":4,"characterId":130,"play":5,"win":2,"mvp":4},{"seasonId":20,"modeId":4,"characterId":137,"play":3,"win":2,"mvp":2},{"seasonId":21,"modeId":4,"characterId":130,"play":2,"win":2,"mvp":1},{"seasonId":22,"modeId":4,"characterId":119,"play":4,"win":2,"mvp":3},{"seasonId":22,"modeId":4,"characterId":130,"play":10,"win":6,"mvp":4},{"seasonId":22,"modeId":4,"characterId":137,"play":1,"win":1,"mvp":1},{"seasonId":23,"modeId":4,"characterId":119,"play":4,"win":0,"mvp":2},{"seasonId":23,"modeId":4,"characterId":130,"play":64,"win":41,"mvp":33},{"seasonId":23,"modeId":4,"characterId":131,"play":3,"win":1,"mvp":2},{"seasonId":23,"modeId":4,"characterId":137,"play":18,"win":10,"mvp":11},{"seasonId":24,"modeId":4,"characterId":115,"play":1,"win":1,"mvp":0},{"seasonId":24,"modeId":4,"characterId":119,"play":1,"win":0,"mvp":0},{"seasonId":24,"modeId":4,"characterId":121,"play":1,"win":0,"mvp":0},{"seasonId":24,"modeId":4,"characterId":130,"play":4,"win":2,"mvp":2},{"seasonId":25,"modeId":4,"characterId":119,"play":1,"win":1,"mvp":1},{"seasonId":25,"modeId":4,"characterId":130,"play":32,"win":22,"mvp":13},{"seasonId":25,"modeId":4,"characterId":131,"play":8,"win":3,"mvp":4},{"seasonId":25,"modeId":4,"characterId":132,"play":1,"win":0,"mvp":0},{"seasonId":25,"modeId":4,"characterId":137,"play":8,"win":5,"mvp":4},{"seasonId":26,"modeId":4,"characterId":119,"play":9,"win":5,"mvp":2},{"seasonId":26,"modeId":4,"characterId":130,"play":99,"win":52,"mvp":40},{"seasonId":26,"modeId":4,"characterId":131,"play":3,"win":2,"mvp":0},{"seasonId":26,"modeId":4,"characterId":132,"play":5,"win":3,"mvp":1},{"seasonId":26,"modeId":4,"characterId":137,"play":22,"win":12,"mvp":5},{"seasonId":27,"modeId":4,"characterId":119,"play":20,"win":11,"mvp":11},{"seasonId":27,"modeId":4,"characterId":130,"play":24,"win":13,"mvp":11},{"seasonId":27,"modeId":4,"characterId":136,"play":5,"win":2,"mvp":1},{"seasonId":27,"modeId":4,"characterId":137,"play":26,"win":16,"mvp":17},{"seasonId":28,"modeId":4,"characterId":119,"play":3,"win":1,"mvp":1},{"seasonId":28,"modeId":4,"characterId":130,"play":14,"win":11,"mvp":6},{"seasonId":28,"modeId":4,"characterId":136,"play":2,"win":1,"mvp":0},{"seasonId":28,"modeId":4,"characterId":137,"play":15,"win":10,"mvp":6},{"seasonId":28,"modeId":4,"characterId":141,"play":19,"win":11,"mvp":8},{"seasonId":29,"modeId":4,"characterId":118,"play":1,"win":1,"mvp":0},{"seasonId":29,"modeId":4,"characterId":119,"play":1,"win":1,"mvp":1},{"seasonId":29,"modeId":4,"characterId":126,"play":1,"win":0,"mvp":0},{"seasonId":29,"modeId":4,"characterId":130,"play":52,"win":35,"mvp":27},{"seasonId":29,"modeId":4,"characterId":132,"play":5,"win":2,"mvp":1},{"seasonId":29,"modeId":4,"characterId":136,"play":10,"win":5,"mvp":3},{"seasonId":29,"modeId":4,"characterId":137,"play":19,"win":8,"mvp":11},{"seasonId":29,"modeId":4,"characterId":141,"play":3,"win":1,"mvp":0},{"seasonId":30,"modeId":4,"characterId":119,"play":1,"win":1,"mvp":1},{"seasonId":30,"modeId":4,"characterId":121,"play":2,"win":1,"mvp":2},{"seasonId":30,"modeId":4,"characterId":130,"play":28,"win":17,"mvp":18},{"seasonId":30,"modeId":4,"characterId":136,"play":34,"win":20,"mvp":17},{"seasonId":30,"modeId":4,"characterId":137,"play":15,"win":8,"mvp":10},{"seasonId":31,"modeId":4,"characterId":119,"play":2,"win":2,"mvp":2},{"seasonId":31,"modeId":4,"characterId":130,"play":29,"win":19,"mvp":23},{"seasonId":31,"modeId":4,"characterId":132,"play":3,"win":1,"mvp":0},{"seasonId":31,"modeId":4,"characterId":136,"play":28,"win":16,"mvp":13},{"seasonId":31,"modeId":4,"characterId":137,"play":47,"win":29,"mvp":18},{"seasonId":31,"modeId":4,"characterId":138,"play":1,"win":0,"mvp":0},{"seasonId":32,"modeId":4,"characterId":130,"play":3,"win":2,"mvp":1},{"seasonId":32,"modeId":4,"characterId":132,"play":1,"win":1,"mvp":0},{"seasonId":32,"modeId":4,"characterId":136,"play":7,"win":4,"mvp":1},{"seasonId":32,"modeId":4,"characterId":137,"play":39,"win":24,"mvp":14},{"seasonId":32,"modeId":4,"characterId":142,"play":1,"win":0,"mvp":0},{"seasonId":33,"modeId":4,"characterId":119,"play":9,"win":5,"mvp":7},{"seasonId":33,"modeId":4,"characterId":130,"play":8,"win":4,"mvp":5},{"seasonId":33,"modeId":4,"characterId":131,"play":4,"win":1,"mvp":1},{"seasonId":33,"modeId":4,"characterId":132,"play":1,"win":0,"mvp":0},{"seasonId":33,"modeId":4,"characterId":136,"play":28,"win":18,"mvp":13},{"seasonId":33,"modeId":4,"characterId":137,"play":19,"win":14,"mvp":6},{"seasonId":33,"modeId":4,"characterId":142,"play":5,"win":2,"mvp":2},{"seasonId":34,"modeId":4,"characterId":130,"play":1,"win":1,"mvp":1},{"seasonId":34,"modeId":4,"characterId":136,"play":3,"win":3,"mvp":2},{"seasonId":34,"modeId":4,"characterId":137,"play":7,"win":7,"mvp":3},{"seasonId":34,"modeId":4,"characterId":142,"play":1,"win":1,"mvp":1},{"seasonId":35,"modeId":4,"characterId":130,"play":2,"win":2,"mvp":2},{"seasonId":35,"modeId":4,"characterId":131,"play":1,"win":1,"mvp":1},{"seasonId":35,"modeId":4,"characterId":136,"play":1,"win":1,"mvp":0},{"seasonId":35,"modeId":4,"characterId":137,"play":11,"win":8,"mvp":6},{"seasonId":35,"modeId":4,"characterId":142,"play":4,"win":3,"mvp":3},{"seasonId":36,"modeId":4,"characterId":119,"play":1,"win":1,"mvp":0},{"seasonId":36,"modeId":4,"characterId":129,"play":1,"win":0,"mvp":0},{"seasonId":36,"modeId":4,"characterId":130,"play":1,"win":0,"mvp":1},{"seasonId":36,"modeId":4,"characterId":131,"play":1,"win":1,"mvp":1},{"seasonId":36,"modeId":4,"characterId":136,"play":5,"win":3,"mvp":2},{"seasonId":36,"modeId":4,"characterId":137,"play":14,"win":13,"mvp":4},{"seasonId":36,"modeId":4,"characterId":142,"play":3,"win":2,"mvp":0},{"seasonId":37,"modeId":4,"characterId":132,"play":5,"win":4,"mvp":1},{"seasonId":37,"modeId":4,"characterId":136,"play":4,"win":2,"mvp":4},{"seasonId":37,"modeId":4,"characterId":137,"play":13,"win":11,"mvp":6},{"seasonId":38,"modeId":4,"characterId":130,"play":3,"win":2,"mvp":1},{"seasonId":38,"modeId":4,"characterId":131,"play":3,"win":1,"mvp":2},{"seasonId":38,"modeId":4,"characterId":136,"play":2,"win":2,"mvp":1},{"seasonId":38,"modeId":4,"characterId":137,"play":13,"win":13,"mvp":5},{"seasonId":38,"modeId":4,"characterId":141,"play":1,"win":1,"mvp":0},{"seasonId":38,"modeId":4,"characterId":142,"play":1,"win":1,"mvp":1},{"seasonId":39,"modeId":4,"characterId":130,"play":12,"win":7,"mvp":7},{"seasonId":39,"modeId":4,"characterId":136,"play":10,"win":5,"mvp":7},{"seasonId":39,"modeId":4,"characterId":137,"play":8,"win":7,"mvp":2},{"seasonId":39,"modeId":4,"characterId":142,"play":2,"win":1,"mvp":0},{"seasonId":40,"modeId":4,"characterId":130,"play":4,"win":3,"mvp":4},{"seasonId":40,"modeId":4,"characterId":136,"play":1,"win":1,"mvp":1},{"seasonId":40,"modeId":4,"characterId":137,"play":1,"win":1,"mvp":0},{"seasonId":41,"modeId":1,"characterId":116,"play":1,"win":1,"mvp":0},{"seasonId":41,"modeId":1,"characterId":130,"play":3,"win":1,"mvp":1},{"seasonId":41,"modeId":1,"characterId":133,"play":1,"win":0,"mvp":1},{"seasonId":41,"modeId":4,"characterId":130,"play":3,"win":2,"mvp":3},{"seasonId":41,"modeId":4,"characterId":136,"play":6,"win":5,"mvp":4},{"seasonId":41,"modeId":4,"characterId":137,"play":1,"win":1,"mvp":1},{"seasonId":41,"modeId":17,"characterId":122,"play":1,"win":0,"mvp":0},{"seasonId":41,"modeId":17,"characterId":130,"play":4,"win":4,"mvp":1},{"seasonId":41,"modeId":99,"characterId":116,"play":1,"win":1,"mvp":0},{"seasonId":41,"modeId":99,"characterId":122,"play":1,"win":0,"mvp":0},{"seasonId":41,"modeId":99,"characterId":130,"play":10,"win":7,"mvp":5},{"seasonId":41,"modeId":99,"characterId":133,"play":1,"win":0,"mvp":1},{"seasonId":41,"modeId":99,"characterId":136,"play":6,"win":5,"mvp":4},{"seasonId":41,"modeId":99,"characterId":137,"play":1,"win":1,"mvp":1},{"seasonId":42,"modeId":4,"characterId":136,"play":1,"win":1,"mvp":1},{"seasonId":42,"modeId":17,"characterId":130,"play":2,"win":2,"mvp":1},{"seasonId":42,"modeId":99,"characterId":130,"play":2,"win":2,"mvp":1},{"seasonId":42,"modeId":99,"characterId":136,"play":1,"win":1,"mvp":1},{"seasonId":43,"modeId":1,"characterId":135,"play":2,"win":1,"mvp":2},{"seasonId":43,"modeId":4,"characterId":130,"play":2,"win":1,"mvp":2},{"seasonId":43,"modeId":17,"characterId":130,"play":4,"win":3,"mvp":3},{"seasonId":43,"modeId":99,"characterId":130,"play":6,"win":4,"mvp":5},{"seasonId":43,"modeId":99,"characterId":135,"play":2,"win":1,"mvp":2},{"seasonId":44,"modeId":1,"characterId":130,"play":2,"win":1,"mvp":1},{"seasonId":44,"modeId":1,"characterId":132,"play":1,"win":1,"mvp":0},{"seasonId":44,"modeId":1,"characterId":135,"play":2,"win":2,"mvp":1},{"seasonId":44,"modeId":4,"characterId":130,"play":3,"win":2,"mvp":3},{"seasonId":44,"modeId":4,"characterId":136,"play":1,"win":0,"mvp":0},{"seasonId":44,"modeId":4,"characterId":137,"play":3,"win":1,"mvp":3},{"seasonId":44,"modeId":17,"characterId":130,"play":3,"win":2,"mvp":3},{"seasonId":44,"modeId":99,"characterId":130,"play":8,"win":5,"mvp":7},{"seasonId":44,"modeId":99,"characterId":132,"play":1,"win":1,"mvp":0},{"seasonId":44,"modeId":99,"characterId":135,"play":2,"win":2,"mvp":1},{"seasonId":44,"modeId":99,"characterId":136,"play":1,"win":0,"mvp":0},{"seasonId":44,"modeId":99,"characterId":137,"play":3,"win":1,"mvp":3}],"mode":[{"modeId":1,"characterId":102,"play":4,"win":4,"mvp":0,"kill":9,"death":4},{"modeId":1,"characterId":103,"play":5,"win":5,"mvp":0,"kill":14,"death":8},{"modeId":1,"characterId":105,"play":2,"win":2,"mvp":1,"kill":8,"death":3},{"modeId":1,"characterId":106,"play":4,"win":4,"mvp":2,"kill":12,"death":1},{"modeId":1,"characterId":109,"play":5,"win":5,"mvp":2,"kill":17,"death":2},{"modeId":1,"characterId":111,"play":5,"win":3,"mvp":2,"kill":15,"death":11},{"modeId":1,"characterId":112,"play":3,"win":3,"mvp":0,"kill":8,"death":4},{"modeId":1,"characterId":113,"play":9,"win":9,"mvp":6,"kill":41,"death":7},{"modeId":1,"characterId":114,"play":9,"win":9,"mvp":1,"kill":23,"death":11},{"modeId":1,"characterId":115,"play":3,"win":1,"mvp":3,"kill":15,"death":7},{"modeId":1,"characterId":118,"play":5,"win":5,"mvp":1,"kill":15,"death":3},{"modeId":1,"characterId":119,"play":9,"win":8,"mvp":6,"kill":35,"death":6},{"modeId":1,"characterId":120,"play":4,"win":2,"mvp":2,"kill":11,"death":8},{"modeId":1,"characterId":121,"play":2,"win":1,"mvp":0,"kill":5,"death":6},{"modeId":1,"characterId":122,"play":25,"win":23,"mvp":12,"kill":81,"death":22},{"modeId":1,"characterId":123,"play":1,"win":1,"mvp":1,"kill":7,"death":2},{"modeId":1,"characterId":125,"play":2,"win":2,"mvp":1,"kill":11,"death":1},{"modeId":1,"characterId":126,"play":3,"win":2,"mvp":2,"kill":12,"death":4},{"modeId":1,"characterId":128,"play":6,"win":5,"mvp":2,"kill":21,"death":8},{"modeId":1,"characterId":129,"play":8,"win":8,"mvp":2,"kill":30,"death":4},{"modeId":1,"characterId":130,"play":74,"win":66,"mvp":50,"kill":327,"death":92},{"modeId":1,"characterId":131,"play":23,"win":21,"mvp":9,"kill":80,"death":24},{"modeId":1,"characterId":132,"play":22,"win":19,"mvp":13,"kill":79,"death":28},{"modeId":1,"characterId":133,"play":5,"win":4,"mvp":4,"kill":28,"death":7},{"modeId":1,"characterId":135,"play":9,"win":8,"mvp":6,"kill":45,"death":14},{"modeId":1,"characterId":136,"play":59,"win":55,"mvp":23,"kill":206,"death":54},{"modeId":1,"characterId":137,"play":20,"win":17,"mvp":7,"kill":62,"death":25},{"modeId":1,"characterId":138,"play":2,"win":2,"mvp":0,"kill":9,"death":4},{"modeId":1,"characterId":139,"play":1,"win":1,"mvp":0,"kill":2,"death":2},{"modeId":1,"characterId":140,"play":1,"win":1,"mvp":1,"kill":6,"death":2},{"modeId":1,"characterId":141,"play":24,"win":19,"mvp":15,"kill":116,"death":36},{"modeId":1,"characterId":142,"play":13,"win":13,"mvp":7,"kill":56,"death":11},{"modeId":1,"characterId":147,"play":4,"win":3,"mvp":4,"kill":24,"death":4},{"modeId":3,"characterId":102,"play":1,"win":0,"mvp":0,"kill":1,"death":3},{"modeId":3,"characterId":104,"play":3,"win":1,"mvp":1,"kill":3,"death":8},{"modeId":3,"characterId":108,"play":3,"win":0,"mvp":0,"kill":1,"death":9},{"modeId":3,"characterId":111,"play":1,"win":1,"mvp":1,"kill":2,"death":1},{"modeId":3,"characterId":112,"play":2,"win":1,"mvp":1,"kill":4,"death":3},{"modeId":3,"characterId":118,"play":3,"win":1,"mvp":1,"kill":5,"death":7},{"modeId":3,"characterId":119,"play":25,"win":14,"mvp":14,"kill":50,"death":46},{"modeId":3,"characterId":122,"play":17,"win":12,"mvp":12,"kill":34,"death":20},{"modeId":3,"characterId":127,"play":16,"win":8,"mvp":8,"kill":33,"death":36},{"modeId":3,"characterId":128,"play":41,"win":28,"mvp":28,"kill":98,"death":61},{"modeId":3,"characterId":130,"play":155,"win":96,"mvp":96,"kill":326,"death":236},{"modeId":3,"characterId":131,"play":55,"win":30,"mvp":30,"kill":108,"death":102},{"modeId":3,"characterId":132,"play":58,"win":29,"mvp":29,"kill":116,"death":109},{"modeId":3,"characterId":133,"play":8,"win":2,"mvp":2,"kill":12,"death":20},{"modeId":3,"characterId":135,"play":7,"win":4,"mvp":4,"kill":15,"death":8},{"modeId":3,"characterId":136,"play":38,"win":21,"mvp":21,"kill":71,"death":71},{"modeId":3,"characterId":137,"play":18,"win":12,"mvp":12,"kill":40,"death":24},{"modeId":3,"characterId":138,"play":10,"win":3,"mvp":3,"kill":15,"death":22},{"modeId":3,"characterId":141,"play":11,"win":6,"mvp":6,"kill":20,"death":23},{"modeId":3,"characterId":142,"play":38,"win":27,"mvp":27,"kill":88,"death":51},{"modeId":4,"characterId":101,"play":20,"win":19,"mvp":9,"kill":76,"death":25},{"modeId":4,"characterId":102,"play":159,"win":123,"mvp":51,"kill":316,"death":150},{"modeId":4,"characterId":103,"play":20,"win":19,"mvp":9,"kill":53,"death":11},{"modeId":4,"characterId":104,"play":71,"win":38,"mvp":32,"kill":199,"death":169},{"modeId":4,"characterId":105,"play":24,"win":18,"mvp":8,"kill":61,"death":40},{"modeId":4,"characterId":106,"play":63,"win":54,"mvp":22,"kill":113,"death":69},{"modeId":4,"characterId":108,"play":29,"win":22,"mvp":9,"kill":109,"death":38},{"modeId":4,"characterId":109,"play":19,"win":17,"mvp":6,"kill":38,"death":17},{"modeId":4,"characterId":110,"play":40,"win":28,"mvp":11,"kill":77,"death":45},{"modeId":4,"characterId":111,"play":84,"win":55,"mvp":45,"kill":219,"death":120},{"modeId":4,"characterId":112,"play":42,"win":33,"mvp":12,"kill":147,"death":70},{"modeId":4,"characterId":113,"play":19,"win":12,"mvp":13,"kill":54,"death":23},{"modeId":4,"characterId":114,"play":7,"win":7,"mvp":0,"kill":23,"death":7},{"modeId":4,"characterId":115,"play":53,"win":38,"mvp":40,"kill":238,"death":99},{"modeId":4,"characterId":116,"play":32,"win":19,"mvp":13,"kill":53,"death":76},{"modeId":4,"characterId":117,"play":38,"win":22,"mvp":27,"kill":183,"death":95},{"modeId":4,"characterId":118,"play":47,"win":43,"mvp":24,"kill":146,"death":23},{"modeId":4,"characterId":119,"play":221,"win":154,"mvp":153,"kill":524,"death":329},{"modeId":4,"characterId":120,"play":22,"win":14,"mvp":9,"kill":41,"death":50},{"modeId":4,"characterId":121,"play":67,"win":56,"mvp":43,"kill":165,"death":58},{"modeId":4,"characterId":122,"play":100,"win":72,"mvp":40,"kill":188,"death":99},{"modeId":4,"characterId":123,"play":40,"win":27,"mvp":27,"kill":130,"death":61},{"modeId":4,"characterId":124,"play":3,"win":2,"mvp":1,"kill":5,"death":4},{"modeId":4,"characterId":125,"play":3,"win":3,"mvp":1,"kill":8,"death":5},{"modeId":4,"characterId":126,"play":40,"win":30,"mvp":21,"kill":101,"death":48},{"modeId":4,"characterId":127,"play":62,"win":36,"mvp":26,"kill":151,"death":141},{"modeId":4,"characterId":128,"play":45,"win":19,"mvp":14,"kill":123,"death":108},{"modeId":4,"characterId":129,"play":17,"win":12,"mvp":9,"kill":28,"death":24},{"modeId":4,"characterId":130,"play":1310,"win":968,"mvp":863,"kill":4667,"death":1750},{"modeId":4,"characterId":131,"play":255,"win":168,"mvp":156,"kill":805,"death":413},{"modeId":4,"characterId":132,"play":381,"win":296,"mvp":195,"kill":1065,"death":580},{"modeId":4,"characterId":133,"play":85,"win":56,"mvp":48,"kill":240,"death":120},{"modeId":4,"characterId":134,"play":19,"win":19,"mvp":5,"kill":57,"death":20},{"modeId":4,"characterId":135,"play":66,"win":50,"mvp":46,"kill":237,"death":105},{"modeId":4,"characterId":136,"play":237,"win":215,"mvp":92,"kill":532,"death":177},{"modeId":4,"characterId":137,"play":326,"win":265,"mvp":169,"kill":880,"death":380},{"modeId":4,"characterId":138,"play":79,"win":48,"mvp":43,"kill":256,"death":174},{"modeId":4,"characterId":139,"play":5,"win":4,"mvp":2,"kill":10,"death":8},{"modeId":4,"characterId":141,"play":98,"win":80,"mvp":40,"kill":283,"death":97},{"modeId":4,"characterId":142,"play":92,"win":82,"mvp":35,"kill":255,"death":73},{"modeId":4,"characterId":143,"play":6,"win":6,"mvp":0,"kill":14,"death":4},{"modeId":4,"characterId":145,"play":11,"win":11,"mvp":8,"kill":48,"death":5},{"modeId":4,"characterId":147,"play":34,"win":31,"mvp":20,"kill":135,"death":17},{"modeId":8,"characterId":102,"play":1,"win":1,"mvp":1,"kill":3,"death":0},{"modeId":8,"characterId":104,"play":1,"win":0,"mvp":0,"kill":1,"death":1},{"modeId":8,"characterId":119,"play":1,"win":0,"mvp":0,"kill":1,"death":1},{"modeId":8,"characterId":122,"play":2,"win":2,"mvp":2,"kill":10,"death":0},{"modeId":8,"characterId":125,"play":2,"win":2,"mvp":1,"kill":9,"death":1},{"modeId":8,"characterId":130,"play":9,"win":8,"mvp":8,"kill":42,"death":1},{"modeId":8,"characterId":131,"play":1,"win":1,"mvp":1,"kill":1,"death":0},{"modeId":8,"characterId":132,"play":1,"win":0,"mvp":0,"kill":2,"death":1},{"modeId":8,"characterId":135,"play":3,"win":3,"mvp":3,"kill":15,"death":0},{"modeId":8,"characterId":136,"play":4,"win":4,"mvp":1,"kill":4,"death":3},{"modeId":8,"characterId":139,"play":3,"win":3,"mvp":3,"kill":15,"death":0},{"modeId":8,"characterId":144,"play":1,"win":1,"mvp":1,"kill":4,"death":0},{"modeId":9,"characterId":102,"play":1,"win":1,"mvp":1,"kill":4,"death":2},{"modeId":9,"characterId":103,"play":1,"win":0,"mvp":0,"kill":0,"death":2},{"modeId":9,"characterId":104,"play":4,"win":2,"mvp":4,"kill":13,"death":8},{"modeId":9,"characterId":110,"play":2,"win":2,"mvp":1,"kill":8,"death":3},{"modeId":9,"characterId":111,"play":3,"win":2,"mvp":1,"kill":10,"death":3},{"modeId":9,"characterId":115,"play":15,"win":11,"mvp":11,"kill":51,"death":18},{"modeId":9,"characterId":117,"play":10,"win":6,"mvp":2,"kill":32,"death":39},{"modeId":9,"characterId":119,"play":11,"win":8,"mvp":3,"kill":23,"death":17},{"modeId":9,"characterId":122,"play":5,"win":3,"mvp":0,"kill":9,"death":8},{"modeId":9,"characterId":125,"play":3,"win":3,"mvp":3,"kill":14,"death":2},{"modeId":9,"characterId":130,"play":77,"win":66,"mvp":44,"kill":246,"death":63},{"modeId":9,"characterId":131,"play":17,"win":14,"mvp":14,"kill":59,"death":14},{"modeId":9,"characterId":132,"play":12,"win":10,"mvp":10,"kill":49,"death":14},{"modeId":9,"characterId":133,"play":4,"win":3,"mvp":3,"kill":13,"death":5},{"modeId":9,"characterId":136,"play":13,"win":12,"mvp":5,"kill":39,"death":7},{"modeId":9,"characterId":137,"play":10,"win":9,"mvp":5,"kill":37,"death":8},{"modeId":9,"characterId":138,"play":4,"win":2,"mvp":2,"kill":15,"death":10},{"modeId":9,"characterId":141,"play":5,"win":3,"mvp":4,"kill":17,"death":2},{"modeId":9,"characterId":142,"play":18,"win":17,"mvp":7,"kill":59,"death":15},{"modeId":9,"characterId":143,"play":2,"win":2,"mvp":2,"kill":12,"death":1},{"modeId":9,"characterId":144,"play":3,"win":3,"mvp":3,"kill":15,"death":1},{"modeId":9,"characterId":147,"play":7,"win":4,"mvp":3,"kill":20,"death":19},{"modeId":14,"characterId":130,"play":17,"win":17,"mvp":16,"kill":166,"death":10},{"modeId":15,"characterId":101,"play":7,"win":5,"mvp":4,"kill":20,"death":12},{"modeId":15,"characterId":102,"play":43,"win":34,"mvp":20,"kill":132,"death":72},{"modeId":15,"characterId":103,"play":1,"win":0,"mvp":1,"kill":1,"death":2},{"modeId":15,"characterId":104,"play":22,"win":15,"mvp":16,"kill":74,"death":37},{"modeId":15,"characterId":105,"play":4,"win":3,"mvp":1,"kill":13,"death":9},{"modeId":15,"characterId":106,"play":12,"win":9,"mvp":4,"kill":27,"death":21},{"modeId":15,"characterId":108,"play":12,"win":9,"mvp":10,"kill":46,"death":16},{"modeId":15,"characterId":109,"play":14,"win":14,"mvp":10,"kill":48,"death":10},{"modeId":15,"characterId":110,"play":2,"win":2,"mvp":2,"kill":9,"death":0},{"modeId":15,"characterId":111,"play":5,"win":4,"mvp":4,"kill":17,"death":11},{"modeId":15,"characterId":112,"play":18,"win":11,"mvp":9,"kill":47,"death":39},{"modeId":15,"characterId":113,"play":9,"win":8,"mvp":8,"kill":31,"death":9},{"modeId":15,"characterId":115,"play":13,"win":9,"mvp":7,"kill":44,"death":27},{"modeId":15,"characterId":117,"play":6,"win":5,"mvp":3,"kill":15,"death":13},{"modeId":15,"characterId":118,"play":29,"win":15,"mvp":22,"kill":76,"death":51},{"modeId":15,"characterId":119,"play":64,"win":52,"mvp":40,"kill":208,"death":82},{"modeId":15,"characterId":120,"play":24,"win":20,"mvp":12,"kill":84,"death":36},{"modeId":15,"characterId":121,"play":23,"win":13,"mvp":12,"kill":63,"death":47},{"modeId":15,"characterId":122,"play":73,"win":57,"mvp":39,"kill":216,"death":100},{"modeId":15,"characterId":124,"play":11,"win":11,"mvp":10,"kill":60,"death":11},{"modeId":15,"characterId":125,"play":10,"win":6,"mvp":8,"kill":35,"death":19},{"modeId":15,"characterId":126,"play":12,"win":7,"mvp":7,"kill":36,"death":18},{"modeId":15,"characterId":127,"play":14,"win":9,"mvp":10,"kill":64,"death":30},{"modeId":15,"characterId":128,"play":12,"win":9,"mvp":7,"kill":37,"death":19},{"modeId":15,"characterId":129,"play":10,"win":8,"mvp":9,"kill":48,"death":11},{"modeId":15,"characterId":130,"play":912,"win":768,"mvp":734,"kill":3783,"death":906},{"modeId":15,"characterId":131,"play":77,"win":57,"mvp":56,"kill":276,"death":97},{"modeId":15,"characterId":132,"play":163,"win":126,"mvp":109,"kill":550,"death":255},{"modeId":15,"characterId":133,"play":58,"win":44,"mvp":43,"kill":194,"death":110},{"modeId":15,"characterId":134,"play":2,"win":0,"mvp":1,"kill":0,"death":7},{"modeId":15,"characterId":135,"play":91,"win":68,"mvp":62,"kill":317,"death":142},{"modeId":15,"characterId":136,"play":199,"win":161,"mvp":129,"kill":688,"death":232},{"modeId":15,"characterId":137,"play":99,"win":79,"mvp":56,"kill":334,"death":125},{"modeId":15,"characterId":138,"play":30,"win":22,"mvp":20,"kill":107,"death":52},{"modeId":15,"characterId":139,"play":12,"win":11,"mvp":6,"kill":41,"death":8},{"modeId":15,"characterId":140,"play":7,"win":7,"mvp":4,"kill":31,"death":10},{"modeId":15,"characterId":141,"play":104,"win":75,"mvp":63,"kill":347,"death":159},{"modeId":15,"characterId":142,"play":149,"win":125,"mvp":84,"kill":490,"death":187},{"modeId":15,"characterId":143,"play":10,"win":10,"mvp":8,"kill":46,"death":10},{"modeId":15,"characterId":144,"play":7,"win":7,"mvp":5,"kill":34,"death":7},{"modeId":15,"characterId":145,"play":65,"win":52,"mvp":59,"kill":276,"death":69},{"modeId":15,"characterId":147,"play":112,"win":89,"mvp":84,"kill":469,"death":177},{"modeId":17,"characterId":102,"play":7,"win":6,"mvp":1,"kill":3,"death":7},{"modeId":17,"characterId":104,"play":3,"win":1,"mvp":3,"kill":16,"death":5},{"modeId":17,"characterId":111,"play":1,"win":1,"mvp":0,"kill":1,"death":0},{"modeId":17,"characterId":113,"play":2,"win":2,"mvp":1,"kill":8,"death":0},{"modeId":17,"characterId":115,"play":6,"win":6,"mvp":5,"kill":23,"death":1},{"modeId":17,"characterId":119,"play":4,"win":4,"mvp":2,"kill":4,"death":1},{"modeId":17,"characterId":121,"play":5,"win":5,"mvp":3,"kill":4,"death":1},{"modeId":17,"characterId":122,"play":20,"win":20,"mvp":12,"kill":70,"death":7},{"modeId":17,"characterId":125,"play":10,"win":9,"mvp":6,"kill":27,"death":4},{"modeId":17,"characterId":127,"play":1,"win":0,"mvp":1,"kill":2,"death":3},{"modeId":17,"characterId":130,"play":120,"win":108,"mvp":48,"kill":244,"death":70},{"modeId":17,"characterId":131,"play":14,"win":14,"mvp":10,"kill":41,"death":1},{"modeId":17,"characterId":132,"play":17,"win":16,"mvp":14,"kill":39,"death":8},{"modeId":17,"characterId":133,"play":4,"win":4,"mvp":4,"kill":24,"death":3},{"modeId":17,"characterId":134,"play":3,"win":3,"mvp":0,"kill":5,"death":2},{"modeId":17,"characterId":135,"play":6,"win":6,"mvp":6,"kill":10,"death":2},{"modeId":17,"characterId":136,"play":12,"win":12,"mvp":7,"kill":18,"death":3},{"modeId":17,"characterId":139,"play":1,"win":1,"mvp":0,"kill":1,"death":1},{"modeId":17,"characterId":142,"play":10,"win":10,"mvp":2,"kill":17,"death":2},{"modeId":17,"characterId":147,"play":12,"win":11,"mvp":7,"kill":41,"death":12},{"modeId":18,"characterId":101,"play":5,"win":3,"mvp":1,"kill":12,"death":19},{"modeId":18,"characterId":102,"play":53,"win":30,"mvp":32,"kill":85,"death":78},{"modeId":18,"characterId":103,"play":21,"win":17,"mvp":10,"kill":60,"death":27},{"modeId":18,"characterId":104,"play":20,"win":16,"mvp":14,"kill":60,"death":42},{"modeId":18,"characterId":105,"play":5,"win":4,"mvp":0,"kill":11,"death":12},{"modeId":18,"characterId":106,"play":42,"win":28,"mvp":32,"kill":52,"death":64},{"modeId":18,"characterId":108,"play":1,"win":1,"mvp":1,"kill":1,"death":0},{"modeId":18,"characterId":109,"play":21,"win":19,"mvp":16,"kill":36,"death":12},{"modeId":18,"characterId":110,"play":12,"win":8,"mvp":9,"kill":18,"death":16},{"modeId":18,"characterId":111,"play":44,"win":24,"mvp":26,"kill":75,"death":103},{"modeId":18,"characterId":112,"play":20,"win":9,"mvp":6,"kill":50,"death":44},{"modeId":18,"characterId":113,"play":14,"win":11,"mvp":6,"kill":19,"death":13},{"modeId":18,"characterId":114,"play":4,"win":4,"mvp":3,"kill":9,"death":3},{"modeId":18,"characterId":115,"play":13,"win":10,"mvp":10,"kill":36,"death":23},{"modeId":18,"characterId":116,"play":19,"win":15,"mvp":9,"kill":38,"death":39},{"modeId":18,"characterId":117,"play":6,"win":5,"mvp":4,"kill":19,"death":12},{"modeId":18,"characterId":118,"play":21,"win":12,"mvp":17,"kill":47,"death":23},{"modeId":18,"characterId":119,"play":82,"win":60,"mvp":59,"kill":138,"death":117},{"modeId":18,"characterId":120,"play":28,"win":20,"mvp":19,"kill":67,"death":63},{"modeId":18,"characterId":121,"play":49,"win":45,"mvp":34,"kill":67,"death":23},{"modeId":18,"characterId":122,"play":191,"win":136,"mvp":107,"kill":353,"death":249},{"modeId":18,"characterId":123,"play":3,"win":3,"mvp":2,"kill":3,"death":7},{"modeId":18,"characterId":124,"play":3,"win":3,"mvp":2,"kill":7,"death":5},{"modeId":18,"characterId":125,"play":59,"win":47,"mvp":52,"kill":156,"death":45},{"modeId":18,"characterId":126,"play":2,"win":2,"mvp":2,"kill":6,"death":2},{"modeId":18,"characterId":127,"play":12,"win":9,"mvp":9,"kill":23,"death":22},{"modeId":18,"characterId":128,"play":14,"win":12,"mvp":9,"kill":52,"death":35},{"modeId":18,"characterId":130,"play":977,"win":780,"mvp":754,"kill":2506,"death":917},{"modeId":18,"characterId":131,"play":133,"win":108,"mvp":102,"kill":294,"death":123},{"modeId":18,"characterId":132,"play":187,"win":137,"mvp":122,"kill":399,"death":348},{"modeId":18,"characterId":133,"play":49,"win":34,"mvp":43,"kill":135,"death":98},{"modeId":18,"characterId":134,"play":2,"win":2,"mvp":2,"kill":7,"death":0},{"modeId":18,"characterId":135,"play":72,"win":51,"mvp":39,"kill":147,"death":90},{"modeId":18,"characterId":136,"play":340,"win":305,"mvp":228,"kill":631,"death":226},{"modeId":18,"characterId":137,"play":98,"win":77,"mvp":59,"kill":218,"death":103},{"modeId":18,"characterId":138,"play":14,"win":14,"mvp":7,"kill":28,"death":12},{"modeId":18,"characterId":139,"play":1,"win":1,"mvp":1,"kill":9,"death":1},{"modeId":18,"characterId":140,"play":26,"win":24,"mvp":25,"kill":70,"death":20},{"modeId":18,"characterId":141,"play":57,"win":45,"mvp":37,"kill":144,"death":74},{"modeId":18,"characterId":142,"play":78,"win":56,"mvp":55,"kill":172,"death":113},{"modeId":18,"characterId":144,"play":3,"win":3,"mvp":3,"kill":8,"death":3},{"modeId":18,"characterId":145,"play":72,"win":57,"mvp":48,"kill":146,"death":75},{"modeId":18,"characterId":147,"play":119,"win":98,"mvp":88,"kill":321,"death":122},{"modeId":20,"characterId":102,"play":3,"win":2,"mvp":0,"kill":3,"death":6},{"modeId":20,"characterId":104,"play":3,"win":2,"mvp":1,"kill":12,"death":6},{"modeId":20,"characterId":113,"play":1,"win":1,"mvp":0,"kill":2,"death":2},{"modeId":20,"characterId":115,"play":2,"win":1,"mvp":1,"kill":9,"death":5},{"modeId":20,"characterId":118,"play":1,"win":1,"mvp":0,"kill":2,"death":2},{"modeId":20,"characterId":119,"play":3,"win":2,"mvp":2,"kill":8,"death":5},{"modeId":20,"characterId":121,"play":1,"win":0,"mvp":0,"kill":3,"death":3},{"modeId":20,"characterId":122,"play":18,"win":16,"mvp":8,"kill":68,"death":26},{"modeId":20,"characterId":124,"play":3,"win":3,"mvp":2,"kill":16,"death":7},{"modeId":20,"characterId":128,"play":3,"win":1,"mvp":3,"kill":15,"death":7},{"modeId":20,"characterId":130,"play":32,"win":26,"mvp":19,"kill":138,"death":52},{"modeId":20,"characterId":131,"play":3,"win":2,"mvp":1,"kill":11,"death":4},{"modeId":20,"characterId":132,"play":17,"win":15,"mvp":1,"kill":53,"death":33},{"modeId":20,"characterId":136,"play":6,"win":2,"mvp":3,"kill":16,"death":15},{"modeId":20,"characterId":137,"play":5,"win":4,"mvp":3,"kill":22,"death":8},{"modeId":20,"characterId":138,"play":4,"win":3,"mvp":1,"kill":13,"death":7},{"modeId":20,"characterId":139,"play":2,"win":1,"mvp":1,"kill":8,"death":5},{"modeId":20,"characterId":141,"play":3,"win":2,"mvp":1,"kill":7,"death":6},{"modeId":20,"characterId":142,"play":15,"win":15,"mvp":6,"kill":57,"death":14},{"modeId":20,"characterId":145,"play":4,"win":2,"mvp":0,"kill":9,"death":9},{"modeId":21,"characterId":102,"play":1,"win":1,"mvp":1,"kill":1,"death":0},{"modeId":21,"characterId":115,"play":4,"win":4,"mvp":4,"kill":12,"death":0},{"modeId":21,"characterId":122,"play":1,"win":1,"mvp":1,"kill":5,"death":0},{"modeId":21,"characterId":125,"play":2,"win":2,"mvp":1,"kill":3,"death":1},{"modeId":21,"characterId":128,"play":1,"win":1,"mvp":1,"kill":3,"death":0},{"modeId":21,"characterId":130,"play":8,"win":6,"mvp":6,"kill":35,"death":2},{"modeId":21,"characterId":132,"play":1,"win":0,"mvp":0,"kill":0,"death":1},{"modeId":21,"characterId":133,"play":7,"win":7,"mvp":6,"kill":27,"death":1},{"modeId":21,"characterId":142,"play":3,"win":2,"mvp":1,"kill":5,"death":2},{"modeId":21,"characterId":144,"play":3,"win":0,"mvp":0,"kill":3,"death":3},{"modeId":21,"characterId":147,"play":3,"win":3,"mvp":1,"kill":7,"death":2},{"modeId":29,"characterId":127,"play":3,"win":2,"mvp":2,"kill":7,"death":4},{"modeId":29,"characterId":131,"play":2,"win":2,"mvp":2,"kill":6,"death":0},{"modeId":29,"characterId":132,"play":14,"win":10,"mvp":10,"kill":33,"death":17},{"modeId":31,"characterId":130,"play":7,"win":7,"mvp":4,"kill":16,"death":2}]},"winningStreak":[{"startsAt":"2025-10-16T18:24:25.000Z","characterId":102,"count":17,"bonusPoint":14,"winLimit":8,"maxCount":17},{"startsAt":"2025-08-16T08:10:18.000Z","characterId":103,"count":3,"bonusPoint":6,"winLimit":8,"maxCount":3},{"startsAt":"2025-10-19T13:22:07.000Z","characterId":104,"count":2,"bonusPoint":4,"winLimit":8,"maxCount":7},{"startsAt":"2025-10-29T19:31:39.000Z","characterId":106,"count":6,"bonusPoint":12,"winLimit":8,"maxCount":9},{"startsAt":"2025-11-01T19:03:33.000Z","characterId":108,"count":1,"bonusPoint":2,"winLimit":8,"maxCount":12},{"startsAt":"2025-10-22T19:00:57.000Z","characterId":109,"count":19,"bonusPoint":14,"winLimit":8,"maxCount":23},{"startsAt":"2025-10-17T17:59:34.000Z","characterId":110,"count":4,"bonusPoint":8,"winLimit":8,"maxCount":7},{"startsAt":"2025-10-13T11:08:24.000Z","characterId":111,"count":0,"bonusPoint":0,"winLimit":8,"maxCount":14},{"startsAt":"2025-10-12T15:15:49.000Z","characterId":112,"count":3,"bonusPoint":6,"winLimit":8,"maxCount":7},{"startsAt":"2025-10-12T15:04:50.000Z","characterId":113,"count":12,"bonusPoint":14,"winLimit":8,"maxCount":12},{"startsAt":"2025-08-23T16:18:01.000Z","characterId":114,"count":7,"bonusPoint":14,"winLimit":8,"maxCount":7},{"startsAt":"2025-10-18T08:54:45.000Z","characterId":115,"count":1,"bonusPoint":2,"winLimit":8,"maxCount":10},{"startsAt":"2025-08-10T12:18:28.000Z","characterId":116,"count":3,"bonusPoint":6,"winLimit":8,"maxCount":5},{"startsAt":"2025-02-02T17:05:34.000Z","characterId":117,"count":2,"bonusPoint":4,"winLimit":8,"maxCount":2},{"startsAt":"2025-11-02T16:39:57.000Z","characterId":118,"count":0,"bonusPoint":0,"winLimit":8,"maxCount":9},{"startsAt":"2025-10-10T19:22:38.000Z","characterId":119,"count":6,"bonusPoint":12,"winLimit":8,"maxCount":16},{"startsAt":"2025-10-13T11:23:02.000Z","characterId":120,"count":2,"bonusPoint":4,"winLimit":8,"maxCount":10},{"startsAt":"2025-10-25T19:26:14.000Z","characterId":121,"count":18,"bonusPoint":14,"winLimit":8,"maxCount":18},{"startsAt":"2025-11-02T19:59:21.000Z","characterId":122,"count":6,"bonusPoint":12,"winLimit":8,"maxCount":30},{"startsAt":"2025-10-25T13:55:26.000Z","characterId":123,"count":3,"bonusPoint":6,"winLimit":8,"maxCount":3},{"startsAt":"2025-08-24T15:08:20.000Z","characterId":124,"count":16,"bonusPoint":14,"winLimit":8,"maxCount":16},{"startsAt":"2025-11-02T16:55:56.000Z","characterId":125,"count":0,"bonusPoint":0,"winLimit":8,"maxCount":14},{"startsAt":"2025-09-17T18:40:40.000Z","characterId":126,"count":1,"bonusPoint":2,"winLimit":8,"maxCount":4},{"startsAt":"2025-10-03T18:40:46.000Z","characterId":127,"count":0,"bonusPoint":0,"winLimit":8,"maxCount":6},{"startsAt":"2025-09-25T18:40:07.000Z","characterId":128,"count":2,"bonusPoint":4,"winLimit":8,"maxCount":12},{"startsAt":"2025-09-24T19:12:19.000Z","characterId":129,"count":2,"bonusPoint":4,"winLimit":8,"maxCount":8},{"startsAt":"2025-11-02T19:13:37.000Z","characterId":130,"count":3,"bonusPoint":6,"winLimit":8,"maxCount":43},{"startsAt":"2025-11-02T18:01:38.000Z","characterId":131,"count":2,"bonusPoint":4,"winLimit":8,"maxCount":16},{"startsAt":"2025-11-02T18:06:22.000Z","characterId":132,"count":9,"bonusPoint":14,"winLimit":8,"maxCount":26},{"startsAt":"2025-10-22T17:56:28.000Z","characterId":133,"count":0,"bonusPoint":0,"winLimit":8,"maxCount":16},{"startsAt":"2025-11-02T19:41:18.000Z","characterId":135,"count":2,"bonusPoint":4,"winLimit":8,"maxCount":13},{"startsAt":"2025-11-02T16:27:37.000Z","characterId":136,"count":5,"bonusPoint":10,"winLimit":8,"maxCount":30},{"startsAt":"2025-10-24T18:02:29.000Z","characterId":137,"count":3,"bonusPoint":6,"winLimit":8,"maxCount":19},{"startsAt":"2025-08-12T16:16:07.000Z","characterId":138,"count":1,"bonusPoint":2,"winLimit":8,"maxCount":6},{"startsAt":"2025-09-21T15:48:58.000Z","characterId":139,"count":5,"bonusPoint":10,"winLimit":8,"maxCount":12},{"startsAt":"2025-10-30T19:33:26.000Z","characterId":140,"count":1,"bonusPoint":2,"winLimit":8,"maxCount":24},{"startsAt":"2025-10-22T18:19:36.000Z","characterId":141,"count":5,"bonusPoint":10,"winLimit":8,"maxCount":33},{"startsAt":"2025-10-21T19:10:14.000Z","characterId":142,"count":0,"bonusPoint":0,"winLimit":8,"maxCount":22},{"startsAt":"2025-09-07T17:23:39.000Z","characterId":143,"count":13,"bonusPoint":14,"winLimit":8,"maxCount":13},{"startsAt":"2025-08-03T15:31:09.000Z","characterId":144,"count":6,"bonusPoint":12,"winLimit":8,"maxCount":10},{"startsAt":"2025-10-05T15:50:37.000Z","characterId":145,"count":0,"bonusPoint":0,"winLimit":8,"maxCount":42},{"startsAt":"2025-10-30T19:38:02.000Z","characterId":147,"count":5,"bonusPoint":10,"winLimit":8,"maxCount":30}]}}