{"fetched_at":1764376491.8874667,"ctype":"application/json; charset=utf-8","body":{"user":{"user_uid":"ep3cbqfyu","nid":null,"gnid":null,"name":"Hishamon","level":281,"exp":687,"trophy":39956,"highestTrophy":39988,"iconId":404044,"frameId":1000106,"createdAt":"2021-04-19T07:43:54.881Z","updatedAt":"2025-11-29T00:34:32.000Z","clan_uid":"pisgjw4zlfqp","clan_name":"SmashPhilippine2","clan_short_name":"PHIL","clan_iconId":0,"growthExp":132,"growthLevel":11,"fortuneExp":594,"fortuneLevel":10,"fame":30040},"compliment":712,"trophy":39988,"rankDetails":[{"user_uid":"ep3cbqfyu","seasonId":1,"modeId":4,"rankPoint":300,"maxRankPoint":328,"tier":"SILVER_3","tierScore":0,"maxTier":"SILVER_3","maxTierScore":28,"remainPlacement":0,"totalPlacement":6,"gameCount":25},{"user_uid":"ep3cbqfyu","seasonId":2,"modeId":4,"rankPoint":527,"maxRankPoint":549,"tier":"SILVER_1","tierScore":27,"maxTier":"SILVER_1","maxTierScore":49,"remainPlacement":0,"totalPlacement":6,"gameCount":28},{"user_uid":"ep3cbqfyu","seasonId":3,"modeId":4,"rankPoint":300,"maxRankPoint":300,"tier":"SILVER_3","tierScore":0,"maxTier":"SILVER_3","maxTierScore":0,"remainPlacement":0,"totalPlacement":6,"gameCount":9},{"user_uid":"ep3cbqfyu","seasonId":4,"modeId":4,"rankPoint":0,"maxRankPoint":0,"tier":"UNRANKED","tierScore":0,"maxTier":"UNRANKED","maxTierScore":0,"remainPlacement":6,"totalPlacement":6,"gameCount":0},{"user_uid":"ep3cbqfyu","seasonId":5,"modeId":4,"rankPoint":50,"maxRankPoint":50,"tier":"BRONZE_3","tierScore":50,"maxTier":"BRONZE_3","maxTierScore":50,"remainPlacement":5,"totalPlacement":6,"gameCount":1},{"user_uid":"ep3cbqfyu","seasonId":6,"modeId":4,"rankPoint":0,"maxRankPoint":0,"tier":"UNRANKED","tierScore":0,"maxTier":"UNRANKED","maxTierScore":0,"remainPlacement":6,"totalPlacement":6,"gameCount":0},{"user_uid":"ep3cbqfyu","seasonId":10,"modeId":4,"rankPoint":729,"maxRankPoint":729,"tier":"GOLD_2","tierScore":29,"maxTier":"GOLD_2","maxTierScore":29,"remainPlacement":0,"totalPlacement":6,"gameCount":7},{"user_uid":"ep3cbqfyu","seasonId":11,"modeId":4,"rankPoint":915,"maxRankPoint":915,"tier":"PLATINUM_3","tierScore":15,"maxTier":"PLATINUM_3","maxTierScore":15,"remainPlacement":0,"totalPlacement":6,"gameCount":6},{"user_uid":"ep3cbqfyu","seasonId":12,"modeId":4,"rankPoint":0,"maxRankPoint":0,"tier":"UNRANKED","tierScore":0,"maxTier":"UNRANKED","maxTierScore":0,"remainPlacement":6,"totalPlacement":6,"gameCount":0},{"user_uid":"ep3cbqfyu","seasonId":16,"modeId":3,"rankPoint":634,"maxRankPoint":634,"tier":"GOLD_3","tierScore":34,"maxTier":"GOLD_3","maxTierScore":34,"remainPlacement":0,"totalPlacement":6,"gameCount":7},{"user_uid":"ep3cbqfyu","seasonId":17,"modeId":3,"rankPoint":0,"maxRankPoint":0,"tier":"UNRANKED","tierScore":0,"maxTier":"UNRANKED","maxTierScore":0,"remainPlacement":6,"totalPlacement":6,"gameCount":0},{"user_uid":"ep3cbqfyu","seasonId":27,"modeId":4,"rankPoint":737,"maxRankPoint":805,"tier":"GOLD_2","tierScore":37,"maxTier":"GOLD_1","maxTierScore":5,"remainPlacement":0,"totalPlacement":6,"gameCount":10},{"user_uid":"ep3cbqfyu","seasonId":28,"modeId":4,"rankPoint":0,"maxRankPoint":0,"tier":"UNRANKED","tierScore":0,"maxTier":"UNRANKED","maxTierScore":0,"remainPlacement":6,"totalPlacement":6,"gameCount":0},{"user_uid":"ep3cbqfyu","seasonId":37,"modeId":4,"rankPoint":662,"maxRankPoint":817,"tier":"GOLD_3","tierScore":62,"maxTier":"GOLD_1","maxTierScore":17,"remainPlacement":0,"totalPlacement":6,"gameCount":66},{"user_uid":"ep3cbqfyu","seasonId":38,"modeId":4,"rankPoint":0,"maxRankPoint":0,"tier":"UNRANKED","tierScore":0,"maxTier":"UNRANKED","maxTierScore":0,"remainPlacement":5,"totalPlacement":6,"gameCount":1},{"user_uid":"ep3cbqfyu","seasonId":39,"modeId":4,"rankPoint":0,"maxRankPoint":0,"tier":"UNRANKED","tierScore":0,"maxTier":"UNRANKED","maxTierScore":0,"remainPlacement":6,"totalPlacement":6,"gameCount":0},{"user_uid":"ep3cbqfyu","seasonId":40,"modeId":4,"rankPoint":0,"maxRankPoint":0,"tier":"UNRANKED","tierScore":0,"maxTier":"UNRANKED","maxTierScore":0,"remainPlacement":5,"totalPlacement":6,"gameCount":1},{"user_uid":"ep3cbqfyu","seasonId":44,"modeId":99,"rankPoint":0,"maxRankPoint":0,"tier":"UNRANKED","tierScore":0,"maxTier":"UNRANKED","maxTierScore":0,"remainPlacement":3,"totalPlacement":6,"gameCount":3},{"user_uid":"ep3cbqfyu","seasonId":45,"modeId":99,"rankPoint":725,"maxRankPoint":791,"tier":"GOLD_2","tierScore":25,"maxTier":"GOLD_2","maxTierScore":91,"remainPlacement":0,"totalPlacement":6,"gameCount":37}],"characters":{"characters":[{"characterId":101,"level":10,"trophy":994,"highestTrophy":1002,"mastery":6498,"unlockedAt":"2022-03-15T04:22:47.000Z","skinItemId":210122,"revivalItemId":910051,"knokoutItemId":0,"finalBlowItemId":930012,"emoticonItemIds":[310101,310102,310108,310109]},{"characterId":102,"level":10,"trophy":1077,"highestTrophy":1077,"mastery":9957,"unlockedAt":"2022-03-15T04:22:47.000Z","skinItemId":210212,"revivalItemId":0,"knokoutItemId":0,"finalBlowItemId":930014,"emoticonItemIds":[310207,310209,310203,310220]},{"characterId":103,"level":10,"trophy":1112,"highestTrophy":1123,"mastery":1721,"unlockedAt":"2022-03-15T04:22:47.000Z","skinItemId":210331,"revivalItemId":910051,"knokoutItemId":0,"finalBlowItemId":930031,"emoticonItemIds":[310308,310309,310307,300016]},{"characterId":104,"level":10,"trophy":1000,"highestTrophy":1000,"mastery":2951,"unlockedAt":"2022-03-15T04:22:47.000Z","skinItemId":0,"revivalItemId":0,"knokoutItemId":0,"finalBlowItemId":0,"emoticonItemIds":[300008,300010,0,0]},{"characterId":105,"level":10,"trophy":1055,"highestTrophy":1063,"mastery":506,"unlockedAt":"2022-03-15T04:22:47.000Z","skinItemId":210516,"revivalItemId":0,"knokoutItemId":0,"finalBlowItemId":0,"emoticonItemIds":[300016,310507,310509,310508]},{"characterId":106,"level":10,"trophy":1000,"highestTrophy":1000,"mastery":1935,"unlockedAt":"2022-03-15T04:22:47.000Z","skinItemId":210623,"revivalItemId":0,"knokoutItemId":0,"finalBlowItemId":0,"emoticonItemIds":[300008,300010,0,0]},{"characterId":108,"level":10,"trophy":1000,"highestTrophy":1000,"mastery":6774,"unlockedAt":"2022-03-15T04:22:47.000Z","skinItemId":210826,"revivalItemId":910023,"knokoutItemId":920026,"finalBlowItemId":930037,"emoticonItemIds":[310801,310807,310808,310804]},{"characterId":109,"level":10,"trophy":186,"highestTrophy":186,"mastery":180,"unlockedAt":"2024-12-19T12:56:17.000Z","skinItemId":210915,"revivalItemId":0,"knokoutItemId":0,"finalBlowItemId":0,"emoticonItemIds":[300008,300010,0,0]},{"characterId":110,"level":10,"trophy":251,"highestTrophy":251,"mastery":150,"unlockedAt":"2022-03-15T04:22:47.000Z","skinItemId":211013,"revivalItemId":0,"knokoutItemId":0,"finalBlowItemId":0,"emoticonItemIds":[300008,300010,0,0]},{"characterId":111,"level":10,"trophy":796,"highestTrophy":808,"mastery":540,"unlockedAt":"2024-01-20T04:45:47.000Z","skinItemId":211102,"revivalItemId":0,"knokoutItemId":0,"finalBlowItemId":0,"emoticonItemIds":[311110,311104,311109,311108]},{"characterId":112,"level":10,"trophy":1000,"highestTrophy":1000,"mastery":4122,"unlockedAt":"2022-03-15T04:22:47.000Z","skinItemId":211226,"revivalItemId":910038,"knokoutItemId":920026,"finalBlowItemId":0,"emoticonItemIds":[300012,311204,311209,311211]},{"characterId":113,"level":10,"trophy":1012,"highestTrophy":1020,"mastery":3817,"unlockedAt":"2022-03-15T04:22:47.000Z","skinItemId":211318,"revivalItemId":910001,"knokoutItemId":0,"finalBlowItemId":930013,"emoticonItemIds":[311301,311304,311307,311309]},{"characterId":114,"level":10,"trophy":470,"highestTrophy":470,"mastery":150,"unlockedAt":"2022-03-15T04:22:47.000Z","skinItemId":0,"revivalItemId":910021,"knokoutItemId":0,"finalBlowItemId":930011,"emoticonItemIds":[311404,311407,311409,311420]},{"characterId":115,"level":10,"trophy":1000,"highestTrophy":1000,"mastery":10350,"unlockedAt":"2022-03-15T04:22:47.000Z","skinItemId":0,"revivalItemId":0,"knokoutItemId":0,"finalBlowItemId":930043,"emoticonItemIds":[311504,311508,311503,311509]},{"characterId":116,"level":10,"trophy":1129,"highestTrophy":1129,"mastery":43655,"unlockedAt":"2022-03-16T08:07:42.000Z","skinItemId":211602,"revivalItemId":910042,"knokoutItemId":0,"finalBlowItemId":930013,"emoticonItemIds":[311601,311602,311608,311603]},{"characterId":117,"level":10,"trophy":1021,"highestTrophy":1021,"mastery":125,"unlockedAt":"2022-03-15T04:22:47.000Z","skinItemId":211716,"revivalItemId":0,"knokoutItemId":0,"finalBlowItemId":930005,"emoticonItemIds":[311708,311704,311707,311709]},{"characterId":118,"level":10,"trophy":1082,"highestTrophy":1082,"mastery":510,"unlockedAt":"2022-03-15T04:22:47.000Z","skinItemId":0,"revivalItemId":0,"knokoutItemId":0,"finalBlowItemId":0,"emoticonItemIds":[300008,300010,0,0]},{"characterId":119,"level":10,"trophy":917,"highestTrophy":917,"mastery":510,"unlockedAt":"2023-06-14T12:19:41.000Z","skinItemId":211902,"revivalItemId":910014,"knokoutItemId":0,"finalBlowItemId":930043,"emoticonItemIds":[300016,311907,311908,311911]},{"characterId":120,"level":10,"trophy":1009,"highestTrophy":1017,"mastery":244,"unlockedAt":"2022-03-17T07:12:29.000Z","skinItemId":212003,"revivalItemId":0,"knokoutItemId":0,"finalBlowItemId":0,"emoticonItemIds":[312004,312007,312008,312009]},{"characterId":121,"level":10,"trophy":303,"highestTrophy":303,"mastery":150,"unlockedAt":"2022-03-15T04:22:47.000Z","skinItemId":212109,"revivalItemId":0,"knokoutItemId":0,"finalBlowItemId":930023,"emoticonItemIds":[312104,312107,312109,0]},{"characterId":122,"level":10,"trophy":1000,"highestTrophy":1000,"mastery":3088,"unlockedAt":"2022-07-15T12:34:10.000Z","skinItemId":212206,"revivalItemId":910032,"knokoutItemId":0,"finalBlowItemId":930014,"emoticonItemIds":[312204,312208,312209,312201]},{"characterId":123,"level":10,"trophy":1000,"highestTrophy":1000,"mastery":2656,"unlockedAt":"2024-01-16T11:46:27.000Z","skinItemId":212303,"revivalItemId":0,"knokoutItemId":0,"finalBlowItemId":930037,"emoticonItemIds":[300008,300010,0,0]},{"characterId":124,"level":10,"trophy":1000,"highestTrophy":1000,"mastery":14489,"unlockedAt":"2022-03-16T09:32:50.000Z","skinItemId":212402,"revivalItemId":0,"knokoutItemId":0,"finalBlowItemId":0,"emoticonItemIds":[312409,312404,312402,312407]},{"characterId":125,"level":10,"trophy":1021,"highestTrophy":1029,"mastery":233,"unlockedAt":"2024-01-16T11:52:11.000Z","skinItemId":212531,"revivalItemId":910001,"knokoutItemId":920014,"finalBlowItemId":930037,"emoticonItemIds":[312508,312504,312507,312509]},{"characterId":126,"level":10,"trophy":168,"highestTrophy":168,"mastery":150,"unlockedAt":"2023-03-14T10:47:37.000Z","skinItemId":0,"revivalItemId":0,"knokoutItemId":0,"finalBlowItemId":930005,"emoticonItemIds":[312609,300010,0,0]},{"characterId":127,"level":10,"trophy":1029,"highestTrophy":1029,"mastery":3498,"unlockedAt":"2022-09-23T12:58:30.000Z","skinItemId":212709,"revivalItemId":910035,"knokoutItemId":0,"finalBlowItemId":930037,"emoticonItemIds":[300016,312704,312702,312707]},{"characterId":128,"level":10,"trophy":1022,"highestTrophy":1022,"mastery":161,"unlockedAt":"2022-08-10T07:16:14.000Z","skinItemId":0,"revivalItemId":0,"knokoutItemId":0,"finalBlowItemId":0,"emoticonItemIds":[300101,312804,312807,312808]},{"characterId":129,"level":10,"trophy":314,"highestTrophy":314,"mastery":150,"unlockedAt":"2024-01-16T11:54:04.000Z","skinItemId":0,"revivalItemId":0,"knokoutItemId":0,"finalBlowItemId":0,"emoticonItemIds":[312910,312907,312909,312908]},{"characterId":130,"level":10,"trophy":1000,"highestTrophy":1000,"mastery":4832,"unlockedAt":"2022-09-11T14:38:00.000Z","skinItemId":213031,"revivalItemId":910059,"knokoutItemId":920014,"finalBlowItemId":930037,"emoticonItemIds":[313008,313004,313007,313009]},{"characterId":131,"level":10,"trophy":1000,"highestTrophy":1000,"mastery":137,"unlockedAt":"2023-03-14T10:50:28.000Z","skinItemId":0,"revivalItemId":0,"knokoutItemId":0,"finalBlowItemId":0,"emoticonItemIds":[300008,300010,0,0]},{"characterId":132,"level":10,"trophy":245,"highestTrophy":245,"mastery":0,"unlockedAt":"2023-03-14T10:52:36.000Z","skinItemId":0,"revivalItemId":0,"knokoutItemId":0,"finalBlowItemId":0,"emoticonItemIds":[300008,300010,0,0]},{"characterId":133,"level":10,"trophy":418,"highestTrophy":418,"mastery":150,"unlockedAt":"2024-01-16T11:55:47.000Z","skinItemId":213302,"revivalItemId":0,"knokoutItemId":0,"finalBlowItemId":0,"emoticonItemIds":[300008,300010,0,0]},{"characterId":134,"level":10,"trophy":1000,"highestTrophy":1000,"mastery":2504,"unlockedAt":"2023-06-09T15:26:51.000Z","skinItemId":0,"revivalItemId":910001,"knokoutItemId":0,"finalBlowItemId":930037,"emoticonItemIds":[313404,313407,313409,313408]},{"characterId":135,"level":10,"trophy":941,"highestTrophy":941,"mastery":150,"unlockedAt":"2024-04-30T09:05:40.000Z","skinItemId":213527,"revivalItemId":0,"knokoutItemId":0,"finalBlowItemId":0,"emoticonItemIds":[300008,300010,0,0]},{"characterId":136,"level":10,"trophy":1000,"highestTrophy":1000,"mastery":137,"unlockedAt":"2024-06-26T12:22:12.000Z","skinItemId":213609,"revivalItemId":0,"knokoutItemId":0,"finalBlowItemId":0,"emoticonItemIds":[313604,313608,313607,313609]},{"characterId":137,"level":10,"trophy":2133,"highestTrophy":2133,"mastery":100010,"unlockedAt":"2023-11-21T09:42:32.000Z","skinItemId":213751,"revivalItemId":910001,"knokoutItemId":0,"finalBlowItemId":930037,"emoticonItemIds":[313701,313704,313703,313708]},{"characterId":138,"level":10,"trophy":1017,"highestTrophy":1017,"mastery":135,"unlockedAt":"2024-07-17T02:21:55.000Z","skinItemId":0,"revivalItemId":0,"knokoutItemId":0,"finalBlowItemId":0,"emoticonItemIds":[300008,300010,0,0]},{"characterId":139,"level":10,"trophy":1000,"highestTrophy":1000,"mastery":1842,"unlockedAt":"2024-04-14T00:33:58.000Z","skinItemId":213909,"revivalItemId":910051,"knokoutItemId":920014,"finalBlowItemId":930012,"emoticonItemIds":[300106,313904,313908,313902]},{"characterId":140,"level":10,"trophy":1017,"highestTrophy":1017,"mastery":484,"unlockedAt":"2024-05-07T11:13:09.000Z","skinItemId":0,"revivalItemId":0,"knokoutItemId":0,"finalBlowItemId":0,"emoticonItemIds":[314008,314007,314009,300016]},{"characterId":141,"level":10,"trophy":518,"highestTrophy":518,"mastery":150,"unlockedAt":"2024-07-16T13:57:48.000Z","skinItemId":0,"revivalItemId":0,"knokoutItemId":0,"finalBlowItemId":0,"emoticonItemIds":[300008,300010,0,0]},{"characterId":142,"level":10,"trophy":158,"highestTrophy":158,"mastery":150,"unlockedAt":"2025-04-11T23:59:32.000Z","skinItemId":0,"revivalItemId":0,"knokoutItemId":0,"finalBlowItemId":0,"emoticonItemIds":[314204,314207,314208,314209]},{"characterId":143,"level":10,"trophy":1000,"highestTrophy":1000,"mastery":1661,"unlockedAt":"2024-11-12T04:23:26.000Z","skinItemId":0,"revivalItemId":0,"knokoutItemId":0,"finalBlowItemId":930012,"emoticonItemIds":[314304,300010,0,0]},{"characterId":144,"level":10,"trophy":158,"highestTrophy":158,"mastery":150,"unlockedAt":"2025-01-05T23:36:41.000Z","skinItemId":214402,"revivalItemId":0,"knokoutItemId":0,"finalBlowItemId":0,"emoticonItemIds":[314404,314407,314408,300104]},{"characterId":145,"level":10,"trophy":1000,"highestTrophy":1000,"mastery":1637,"unlockedAt":"2025-01-11T03:10:55.000Z","skinItemId":0,"revivalItemId":0,"knokoutItemId":0,"finalBlowItemId":0,"emoticonItemIds":[300008,300010,0,0]},{"characterId":147,"level":10,"trophy":1017,"highestTrophy":1017,"mastery":10011,"unlockedAt":"2025-08-05T00:51:01.000Z","skinItemId":214701,"revivalItemId":910051,"knokoutItemId":0,"finalBlowItemId":930026,"emoticonItemIds":[314704,314703,314702,314709]},{"characterId":148,"level":10,"trophy":1366,"highestTrophy":1514,"mastery":8610,"unlockedAt":"2025-11-10T06:10:24.000Z","skinItemId":214801,"revivalItemId":910037,"knokoutItemId":0,"finalBlowItemId":930014,"emoticonItemIds":[300015,300012,300006,300016]}]},"statsAll":{"competitive":[{"seasonId":1,"modeId":4,"characterId":106,"play":1,"win":0,"mvp":0},{"seasonId":1,"modeId":4,"characterId":116,"play":22,"win":8,"mvp":14},{"seasonId":1,"modeId":4,"characterId":118,"play":2,"win":0,"mvp":1},{"seasonId":2,"modeId":4,"characterId":106,"play":20,"win":9,"mvp":4},{"seasonId":2,"modeId":4,"characterId":116,"play":8,"win":4,"mvp":1},{"seasonId":3,"modeId":4,"characterId":101,"play":3,"win":2,"mvp":1},{"seasonId":3,"modeId":4,"characterId":102,"play":1,"win":0,"mvp":0},{"seasonId":3,"modeId":4,"characterId":115,"play":1,"win":0,"mvp":0},{"seasonId":3,"modeId":4,"characterId":116,"play":1,"win":1,"mvp":0},{"seasonId":3,"modeId":4,"characterId":122,"play":1,"win":1,"mvp":0},{"seasonId":3,"modeId":4,"characterId":124,"play":2,"win":2,"mvp":2},{"seasonId":5,"modeId":4,"characterId":116,"play":1,"win":1,"mvp":0},{"seasonId":10,"modeId":4,"characterId":101,"play":2,"win":1,"mvp":1},{"seasonId":10,"modeId":4,"characterId":116,"play":5,"win":4,"mvp":5},{"seasonId":11,"modeId":4,"characterId":116,"play":6,"win":6,"mvp":3},{"seasonId":16,"modeId":3,"characterId":124,"play":7,"win":5,"mvp":5},{"seasonId":27,"modeId":4,"characterId":106,"play":1,"win":0,"mvp":1},{"seasonId":27,"modeId":4,"characterId":112,"play":1,"win":1,"mvp":1},{"seasonId":27,"modeId":4,"characterId":115,"play":2,"win":1,"mvp":1},{"seasonId":27,"modeId":4,"characterId":116,"play":3,"win":2,"mvp":2},{"seasonId":27,"modeId":4,"characterId":137,"play":2,"win":2,"mvp":1},{"seasonId":27,"modeId":4,"characterId":140,"play":1,"win":1,"mvp":1},{"seasonId":37,"modeId":4,"characterId":101,"play":1,"win":0,"mvp":0},{"seasonId":37,"modeId":4,"characterId":113,"play":2,"win":1,"mvp":1},{"seasonId":37,"modeId":4,"characterId":136,"play":1,"win":0,"mvp":0},{"seasonId":37,"modeId":4,"characterId":137,"play":61,"win":31,"mvp":20},{"seasonId":37,"modeId":4,"characterId":140,"play":1,"win":0,"mvp":0},{"seasonId":38,"modeId":4,"characterId":137,"play":1,"win":1,"mvp":1},{"seasonId":40,"modeId":4,"characterId":137,"play":1,"win":1,"mvp":1},{"seasonId":44,"modeId":1,"characterId":137,"play":1,"win":0,"mvp":0},{"seasonId":44,"modeId":1,"characterId":147,"play":1,"win":1,"mvp":1},{"seasonId":44,"modeId":17,"characterId":137,"play":1,"win":0,"mvp":1},{"seasonId":44,"modeId":99,"characterId":137,"play":2,"win":0,"mvp":1},{"seasonId":44,"modeId":99,"characterId":147,"play":1,"win":1,"mvp":1},{"seasonId":45,"modeId":1,"characterId":103,"play":1,"win":0,"mvp":0},{"seasonId":45,"modeId":1,"characterId":120,"play":1,"win":1,"mvp":1},{"seasonId":45,"modeId":1,"characterId":134,"play":2,"win":1,"mvp":1},{"seasonId":45,"modeId":1,"characterId":137,"play":8,"win":3,"mvp":5},{"seasonId":45,"modeId":1,"characterId":147,"play":1,"win":1,"mvp":0},{"seasonId":45,"modeId":4,"characterId":137,"play":8,"win":5,"mvp":1},{"seasonId":45,"modeId":17,"characterId":137,"play":16,"win":11,"mvp":3},{"seasonId":45,"modeId":99,"characterId":103,"play":1,"win":0,"mvp":0},{"seasonId":45,"modeId":99,"characterId":120,"play":1,"win":1,"mvp":1},{"seasonId":45,"modeId":99,"characterId":134,"play":2,"win":1,"mvp":1},{"seasonId":45,"modeId":99,"characterId":137,"play":32,"win":19,"mvp":9},{"seasonId":45,"modeId":99,"characterId":147,"play":1,"win":1,"mvp":0}],"mode":[{"modeId":1,"characterId":105,"play":12,"win":10,"mvp":6,"kill":44,"death":22},{"modeId":1,"characterId":116,"play":12,"win":9,"mvp":11,"kill":59,"death":13},{"modeId":1,"characterId":117,"play":12,"win":6,"mvp":9,"kill":48,"death":27},{"modeId":1,"characterId":122,"play":1,"win":0,"mvp":1,"kill":3,"death":3},{"modeId":1,"characterId":124,"play":5,"win":3,"mvp":2,"kill":20,"death":7},{"modeId":1,"characterId":137,"play":14,"win":5,"mvp":9,"kill":40,"death":31},{"modeId":1,"characterId":138,"play":2,"win":1,"mvp":0,"kill":6,"death":5},{"modeId":3,"characterId":101,"play":252,"win":147,"mvp":147,"kill":506,"death":447},{"modeId":3,"characterId":102,"play":384,"win":205,"mvp":205,"kill":656,"death":641},{"modeId":3,"characterId":103,"play":100,"win":69,"mvp":69,"kill":224,"death":143},{"modeId":3,"characterId":104,"play":83,"win":36,"mvp":34,"kill":125,"death":171},{"modeId":3,"characterId":105,"play":37,"win":22,"mvp":22,"kill":76,"death":58},{"modeId":3,"characterId":106,"play":33,"win":14,"mvp":14,"kill":54,"death":64},{"modeId":3,"characterId":108,"play":385,"win":206,"mvp":206,"kill":761,"death":718},{"modeId":3,"characterId":109,"play":7,"win":6,"mvp":6,"kill":16,"death":6},{"modeId":3,"characterId":110,"play":8,"win":5,"mvp":5,"kill":18,"death":10},{"modeId":3,"characterId":111,"play":22,"win":20,"mvp":20,"kill":57,"death":15},{"modeId":3,"characterId":112,"play":231,"win":135,"mvp":135,"kill":448,"death":400},{"modeId":3,"characterId":113,"play":226,"win":112,"mvp":112,"kill":424,"death":426},{"modeId":3,"characterId":114,"play":20,"win":15,"mvp":15,"kill":44,"death":31},{"modeId":3,"characterId":115,"play":354,"win":218,"mvp":218,"kill":709,"death":569},{"modeId":3,"characterId":116,"play":1600,"win":969,"mvp":899,"kill":3395,"death":2783},{"modeId":3,"characterId":117,"play":37,"win":27,"mvp":27,"kill":75,"death":54},{"modeId":3,"characterId":118,"play":51,"win":37,"mvp":34,"kill":129,"death":73},{"modeId":3,"characterId":119,"play":31,"win":25,"mvp":25,"kill":64,"death":28},{"modeId":3,"characterId":120,"play":76,"win":35,"mvp":32,"kill":121,"death":155},{"modeId":3,"characterId":121,"play":8,"win":7,"mvp":7,"kill":20,"death":5},{"modeId":3,"characterId":122,"play":213,"win":117,"mvp":117,"kill":390,"death":361},{"modeId":3,"characterId":123,"play":144,"win":101,"mvp":101,"kill":344,"death":222},{"modeId":3,"characterId":124,"play":706,"win":456,"mvp":452,"kill":1525,"death":1119},{"modeId":3,"characterId":125,"play":39,"win":29,"mvp":29,"kill":94,"death":41},{"modeId":3,"characterId":126,"play":6,"win":5,"mvp":5,"kill":15,"death":3},{"modeId":3,"characterId":127,"play":164,"win":111,"mvp":111,"kill":349,"death":259},{"modeId":3,"characterId":128,"play":47,"win":32,"mvp":32,"kill":98,"death":70},{"modeId":3,"characterId":129,"play":11,"win":10,"mvp":10,"kill":30,"death":7},{"modeId":3,"characterId":130,"play":204,"win":83,"mvp":83,"kill":321,"death":420},{"modeId":3,"characterId":131,"play":37,"win":28,"mvp":28,"kill":83,"death":46},{"modeId":3,"characterId":132,"play":18,"win":13,"mvp":13,"kill":41,"death":26},{"modeId":3,"characterId":133,"play":19,"win":15,"mvp":15,"kill":42,"death":23},{"modeId":3,"characterId":134,"play":134,"win":69,"mvp":69,"kill":252,"death":240},{"modeId":3,"characterId":135,"play":40,"win":28,"mvp":28,"kill":90,"death":56},{"modeId":3,"characterId":136,"play":81,"win":43,"mvp":43,"kill":147,"death":129},{"modeId":3,"characterId":137,"play":2236,"win":1399,"mvp":1399,"kill":4400,"death":3271},{"modeId":3,"characterId":138,"play":33,"win":27,"mvp":27,"kill":86,"death":21},{"modeId":3,"characterId":139,"play":157,"win":89,"mvp":89,"kill":322,"death":276},{"modeId":3,"characterId":140,"play":57,"win":37,"mvp":37,"kill":115,"death":90},{"modeId":3,"characterId":141,"play":45,"win":26,"mvp":26,"kill":84,"death":64},{"modeId":3,"characterId":142,"play":5,"win":5,"mvp":5,"kill":14,"death":0},{"modeId":3,"characterId":143,"play":122,"win":72,"mvp":72,"kill":246,"death":199},{"modeId":3,"characterId":144,"play":5,"win":5,"mvp":5,"kill":14,"death":0},{"modeId":3,"characterId":145,"play":104,"win":69,"mvp":69,"kill":233,"death":149},{"modeId":3,"characterId":147,"play":382,"win":259,"mvp":259,"kill":874,"death":543},{"modeId":3,"characterId":148,"play":266,"win":160,"mvp":160,"kill":526,"death":409},{"modeId":4,"characterId":101,"play":74,"win":37,"mvp":28,"kill":190,"death":148},{"modeId":4,"characterId":102,"play":205,"win":107,"mvp":57,"kill":28,"death":22},{"modeId":4,"characterId":103,"play":17,"win":12,"mvp":3,"kill":36,"death":36},{"modeId":4,"characterId":104,"play":55,"win":30,"mvp":9,"kill":58,"death":59},{"modeId":4,"characterId":105,"play":6,"win":4,"mvp":6,"kill":22,"death":8},{"modeId":4,"characterId":106,"play":86,"win":46,"mvp":31,"kill":36,"death":36},{"modeId":4,"characterId":108,"play":46,"win":21,"mvp":12,"kill":102,"death":90},{"modeId":4,"characterId":111,"play":5,"win":5,"mvp":5,"kill":19,"death":1},{"modeId":4,"characterId":112,"play":18,"win":8,"mvp":10,"kill":40,"death":38},{"modeId":4,"characterId":113,"play":23,"win":7,"mvp":10,"kill":57,"death":51},{"modeId":4,"characterId":114,"play":8,"win":4,"mvp":1,"kill":6,"death":20},{"modeId":4,"characterId":115,"play":148,"win":80,"mvp":63,"kill":132,"death":103},{"modeId":4,"characterId":116,"play":945,"win":553,"mvp":491,"kill":1472,"death":1105},{"modeId":4,"characterId":118,"play":32,"win":21,"mvp":11,"kill":0,"death":0},{"modeId":4,"characterId":120,"play":20,"win":12,"mvp":4,"kill":0,"death":0},{"modeId":4,"characterId":122,"play":31,"win":17,"mvp":17,"kill":86,"death":56},{"modeId":4,"characterId":123,"play":1,"win":0,"mvp":1,"kill":0,"death":0},{"modeId":4,"characterId":124,"play":134,"win":69,"mvp":27,"kill":209,"death":190},{"modeId":4,"characterId":127,"play":7,"win":1,"mvp":3,"kill":13,"death":11},{"modeId":4,"characterId":128,"play":1,"win":1,"mvp":0,"kill":1,"death":2},{"modeId":4,"characterId":130,"play":20,"win":9,"mvp":6,"kill":53,"death":52},{"modeId":4,"characterId":131,"play":16,"win":9,"mvp":8,"kill":41,"death":30},{"modeId":4,"characterId":134,"play":44,"win":17,"mvp":12,"kill":98,"death":94},{"modeId":4,"characterId":136,"play":2,"win":1,"mvp":0,"kill":6,"death":8},{"modeId":4,"characterId":137,"play":233,"win":135,"mvp":110,"kill":432,"death":376},{"modeId":4,"characterId":138,"play":1,"win":0,"mvp":1,"kill":3,"death":4},{"modeId":4,"characterId":140,"play":2,"win":1,"mvp":0,"kill":3,"death":1},{"modeId":4,"characterId":143,"play":3,"win":1,"mvp":1,"kill":7,"death":7},{"modeId":4,"characterId":145,"play":17,"win":8,"mvp":10,"kill":53,"death":28},{"modeId":4,"characterId":147,"play":5,"win":5,"mvp":2,"kill":20,"death":10},{"modeId":4,"characterId":148,"play":6,"win":2,"mvp":5,"kill":13,"death":13},{"modeId":8,"characterId":116,"play":7,"win":7,"mvp":5,"kill":23,"death":2},{"modeId":8,"characterId":119,"play":2,"win":2,"mvp":2,"kill":4,"death":0},{"modeId":8,"characterId":124,"play":1,"win":1,"mvp":1,"kill":3,"death":0},{"modeId":8,"characterId":125,"play":1,"win":1,"mvp":1,"kill":4,"death":0},{"modeId":8,"characterId":137,"play":217,"win":211,"mvp":155,"kill":560,"death":62},{"modeId":8,"characterId":143,"play":4,"win":3,"mvp":2,"kill":8,"death":2},{"modeId":8,"characterId":148,"play":132,"win":127,"mvp":71,"kill":265,"death":61},{"modeId":9,"characterId":104,"play":7,"win":5,"mvp":4,"kill":18,"death":9},{"modeId":9,"characterId":113,"play":5,"win":4,"mvp":3,"kill":16,"death":7},{"modeId":9,"characterId":122,"play":1,"win":1,"mvp":0,"kill":3,"death":0},{"modeId":9,"characterId":137,"play":11,"win":7,"mvp":3,"kill":35,"death":15},{"modeId":9,"characterId":138,"play":4,"win":3,"mvp":3,"kill":23,"death":5},{"modeId":9,"characterId":147,"play":4,"win":4,"mvp":0,"kill":7,"death":2},{"modeId":14,"characterId":101,"play":2,"win":2,"mvp":0,"kill":11,"death":3},{"modeId":14,"characterId":103,"play":1,"win":1,"mvp":1,"kill":11,"death":1},{"modeId":14,"characterId":105,"play":4,"win":4,"mvp":2,"kill":17,"death":4},{"modeId":14,"characterId":106,"play":5,"win":5,"mvp":4,"kill":24,"death":7},{"modeId":14,"characterId":111,"play":3,"win":3,"mvp":3,"kill":25,"death":3},{"modeId":14,"characterId":115,"play":4,"win":4,"mvp":2,"kill":16,"death":9},{"modeId":14,"characterId":116,"play":2,"win":2,"mvp":2,"kill":15,"death":1},{"modeId":14,"characterId":117,"play":3,"win":2,"mvp":1,"kill":16,"death":5},{"modeId":14,"characterId":119,"play":5,"win":5,"mvp":5,"kill":42,"death":3},{"modeId":14,"characterId":120,"play":1,"win":1,"mvp":0,"kill":2,"death":2},{"modeId":14,"characterId":127,"play":7,"win":6,"mvp":6,"kill":50,"death":9},{"modeId":14,"characterId":134,"play":6,"win":5,"mvp":3,"kill":33,"death":8},{"modeId":14,"characterId":135,"play":2,"win":2,"mvp":2,"kill":16,"death":3},{"modeId":14,"characterId":136,"play":1,"win":1,"mvp":1,"kill":3,"death":1},{"modeId":14,"characterId":137,"play":256,"win":255,"mvp":211,"kill":1400,"death":209},{"modeId":14,"characterId":139,"play":10,"win":9,"mvp":4,"kill":63,"death":20},{"modeId":14,"characterId":143,"play":5,"win":5,"mvp":5,"kill":28,"death":6},{"modeId":14,"characterId":145,"play":1,"win":1,"mvp":1,"kill":8,"death":1},{"modeId":14,"characterId":147,"play":27,"win":27,"mvp":23,"kill":212,"death":29},{"modeId":15,"characterId":102,"play":3,"win":2,"mvp":3,"kill":13,"death":6},{"modeId":15,"characterId":105,"play":2,"win":2,"mvp":1,"kill":4,"death":6},{"modeId":15,"characterId":106,"play":2,"win":1,"mvp":0,"kill":2,"death":5},{"modeId":15,"characterId":108,"play":3,"win":3,"mvp":2,"kill":11,"death":2},{"modeId":15,"characterId":112,"play":1,"win":1,"mvp":1,"kill":6,"death":1},{"modeId":15,"characterId":115,"play":5,"win":3,"mvp":2,"kill":15,"death":5},{"modeId":15,"characterId":116,"play":8,"win":6,"mvp":6,"kill":34,"death":15},{"modeId":15,"characterId":120,"play":3,"win":0,"mvp":3,"kill":4,"death":8},{"modeId":15,"characterId":123,"play":9,"win":9,"mvp":7,"kill":35,"death":11},{"modeId":15,"characterId":124,"play":2,"win":0,"mvp":1,"kill":5,"death":6},{"modeId":15,"characterId":127,"play":1,"win":1,"mvp":0,"kill":1,"death":1},{"modeId":15,"characterId":130,"play":13,"win":8,"mvp":4,"kill":31,"death":31},{"modeId":15,"characterId":134,"play":3,"win":2,"mvp":2,"kill":6,"death":3},{"modeId":15,"characterId":135,"play":3,"win":3,"mvp":3,"kill":17,"death":2},{"modeId":15,"characterId":137,"play":445,"win":285,"mvp":310,"kill":1529,"death":704},{"modeId":15,"characterId":140,"play":3,"win":3,"mvp":2,"kill":11,"death":3},{"modeId":15,"characterId":145,"play":2,"win":1,"mvp":2,"kill":8,"death":3},{"modeId":15,"characterId":147,"play":16,"win":10,"mvp":9,"kill":57,"death":35},{"modeId":15,"characterId":148,"play":2,"win":2,"mvp":2,"kill":9,"death":4},{"modeId":17,"characterId":101,"play":50,"win":34,"mvp":20,"kill":152,"death":121},{"modeId":17,"characterId":102,"play":24,"win":14,"mvp":9,"kill":61,"death":41},{"modeId":17,"characterId":104,"play":2,"win":0,"mvp":1,"kill":4,"death":3},{"modeId":17,"characterId":105,"play":1,"win":1,"mvp":0,"kill":5,"death":1},{"modeId":17,"characterId":106,"play":4,"win":2,"mvp":4,"kill":11,"death":10},{"modeId":17,"characterId":108,"play":14,"win":9,"mvp":7,"kill":58,"death":25},{"modeId":17,"characterId":110,"play":1,"win":1,"mvp":0,"kill":3,"death":0},{"modeId":17,"characterId":112,"play":29,"win":16,"mvp":15,"kill":91,"death":82},{"modeId":17,"characterId":113,"play":2,"win":1,"mvp":1,"kill":5,"death":7},{"modeId":17,"characterId":115,"play":43,"win":30,"mvp":32,"kill":159,"death":71},{"modeId":17,"characterId":116,"play":68,"win":44,"mvp":44,"kill":234,"death":170},{"modeId":17,"characterId":118,"play":5,"win":2,"mvp":5,"kill":19,"death":5},{"modeId":17,"characterId":120,"play":2,"win":2,"mvp":0,"kill":4,"death":0},{"modeId":17,"characterId":122,"play":22,"win":14,"mvp":11,"kill":56,"death":73},{"modeId":17,"characterId":124,"play":33,"win":20,"mvp":12,"kill":86,"death":73},{"modeId":17,"characterId":128,"play":1,"win":1,"mvp":0,"kill":3,"death":4},{"modeId":17,"characterId":130,"play":35,"win":15,"mvp":9,"kill":71,"death":99},{"modeId":17,"characterId":134,"play":3,"win":0,"mvp":1,"kill":4,"death":13},{"modeId":17,"characterId":137,"play":40,"win":28,"mvp":30,"kill":117,"death":40},{"modeId":17,"characterId":143,"play":1,"win":1,"mvp":1,"kill":5,"death":5},{"modeId":18,"characterId":101,"play":3,"win":2,"mvp":3,"kill":17,"death":6},{"modeId":18,"characterId":102,"play":5,"win":0,"mvp":3,"kill":9,"death":13},{"modeId":18,"characterId":103,"play":5,"win":3,"mvp":2,"kill":3,"death":4},{"modeId":18,"characterId":104,"play":6,"win":4,"mvp":4,"kill":17,"death":13},{"modeId":18,"characterId":105,"play":1,"win":1,"mvp":0,"kill":1,"death":1},{"modeId":18,"characterId":106,"play":3,"win":2,"mvp":1,"kill":7,"death":4},{"modeId":18,"characterId":108,"play":13,"win":9,"mvp":7,"kill":30,"death":23},{"modeId":18,"characterId":112,"play":3,"win":0,"mvp":1,"kill":4,"death":8},{"modeId":18,"characterId":113,"play":40,"win":26,"mvp":25,"kill":102,"death":69},{"modeId":18,"characterId":115,"play":1,"win":0,"mvp":0,"kill":0,"death":2},{"modeId":18,"characterId":116,"play":83,"win":62,"mvp":65,"kill":221,"death":168},{"modeId":18,"characterId":118,"play":5,"win":3,"mvp":5,"kill":11,"death":6},{"modeId":18,"characterId":119,"play":1,"win":1,"mvp":1,"kill":1,"death":0},{"modeId":18,"characterId":120,"play":2,"win":0,"mvp":1,"kill":1,"death":4},{"modeId":18,"characterId":122,"play":2,"win":1,"mvp":1,"kill":5,"death":3},{"modeId":18,"characterId":124,"play":50,"win":27,"mvp":31,"kill":131,"death":120},{"modeId":18,"characterId":126,"play":1,"win":0,"mvp":0,"kill":1,"death":3},{"modeId":18,"characterId":127,"play":24,"win":15,"mvp":14,"kill":64,"death":72},{"modeId":18,"characterId":128,"play":2,"win":1,"mvp":1,"kill":2,"death":6},{"modeId":18,"characterId":130,"play":108,"win":66,"mvp":67,"kill":249,"death":206},{"modeId":18,"characterId":131,"play":2,"win":1,"mvp":1,"kill":0,"death":4},{"modeId":18,"characterId":134,"play":10,"win":6,"mvp":5,"kill":26,"death":22},{"modeId":18,"characterId":137,"play":455,"win":335,"mvp":299,"kill":909,"death":578},{"modeId":18,"characterId":139,"play":1,"win":1,"mvp":1,"kill":6,"death":2},{"modeId":18,"characterId":143,"play":5,"win":3,"mvp":5,"kill":10,"death":5},{"modeId":18,"characterId":145,"play":3,"win":2,"mvp":2,"kill":4,"death":5},{"modeId":18,"characterId":147,"play":9,"win":6,"mvp":4,"kill":17,"death":13},{"modeId":20,"characterId":116,"play":19,"win":12,"mvp":12,"kill":70,"death":38},{"modeId":20,"characterId":137,"play":31,"win":19,"mvp":13,"kill":89,"death":64},{"modeId":21,"characterId":127,"play":7,"win":6,"mvp":5,"kill":18,"death":2},{"modeId":21,"characterId":137,"play":29,"win":29,"mvp":21,"kill":73,"death":8},{"modeId":29,"characterId":102,"play":2,"win":0,"mvp":0,"kill":1,"death":6},{"modeId":29,"characterId":115,"play":4,"win":0,"mvp":0,"kill":4,"death":11},{"modeId":29,"characterId":122,"play":2,"win":1,"mvp":1,"kill":5,"death":4},{"modeId":29,"characterId":125,"play":4,"win":4,"mvp":4,"kill":11,"death":2},{"modeId":29,"characterId":137,"play":256,"win":173,"mvp":173,"kill":563,"death":345},{"modeId":29,"characterId":140,"play":12,"win":6,"mvp":6,"kill":20,"death":23},{"modeId":31,"characterId":137,"play":31,"win":22,"mvp":28,"kill":84,"death":24}]},"winningStreak":[{"startsAt":"2025-11-04T23:50:02.000Z","characterId":101,"count":0,"bonusPoint":0,"winLimit":6,"maxCount":9},{"startsAt":"2025-11-20T08:33:15.000Z","characterId":102,"count":2,"bonusPoint":2,"winLimit":6,"maxCount":13},{"startsAt":"2025-11-26T10:07:52.000Z","characterId":103,"count":0,"bonusPoint":0,"winLimit":6,"maxCount":13},{"startsAt":"2025-06-04T10:25:53.000Z","characterId":104,"count":0,"bonusPoint":0,"winLimit":6,"maxCount":4},{"startsAt":"2025-11-09T16:35:42.000Z","characterId":105,"count":1,"bonusPoint":1,"winLimit":6,"maxCount":9},{"startsAt":"2025-07-22T11:55:45.000Z","characterId":106,"count":5,"bonusPoint":5,"winLimit":6,"maxCount":5},{"startsAt":"2025-10-17T04:58:54.000Z","characterId":108,"count":0,"bonusPoint":0,"winLimit":6,"maxCount":6},{"startsAt":"2025-11-09T08:05:26.000Z","characterId":109,"count":1,"bonusPoint":1,"winLimit":6,"maxCount":5},{"startsAt":"2025-11-10T06:09:09.000Z","characterId":110,"count":3,"bonusPoint":3,"winLimit":6,"maxCount":3},{"startsAt":"2025-11-09T15:27:50.000Z","characterId":111,"count":0,"bonusPoint":0,"winLimit":6,"maxCount":28},{"startsAt":"2025-10-05T08:59:51.000Z","characterId":112,"count":0,"bonusPoint":0,"winLimit":6,"maxCount":3},{"startsAt":"2025-11-29T00:34:24.000Z","characterId":113,"count":1,"bonusPoint":1,"winLimit":6,"maxCount":4},{"startsAt":"2025-11-08T10:54:29.000Z","characterId":114,"count":4,"bonusPoint":4,"winLimit":6,"maxCount":4},{"startsAt":"2025-07-24T09:07:17.000Z","characterId":115,"count":4,"bonusPoint":4,"winLimit":6,"maxCount":6},{"startsAt":"2025-11-26T10:00:36.000Z","characterId":116,"count":5,"bonusPoint":5,"winLimit":6,"maxCount":10},{"startsAt":"2025-11-09T16:09:05.000Z","characterId":117,"count":4,"bonusPoint":4,"winLimit":6,"maxCount":4},{"startsAt":"2025-11-09T14:53:27.000Z","characterId":118,"count":6,"bonusPoint":5,"winLimit":6,"maxCount":14},{"startsAt":"2025-11-10T05:22:03.000Z","characterId":119,"count":7,"bonusPoint":5,"winLimit":6,"maxCount":19},{"startsAt":"2025-11-09T15:05:08.000Z","characterId":120,"count":0,"bonusPoint":0,"winLimit":6,"maxCount":5},{"startsAt":"2025-11-07T11:44:33.000Z","characterId":121,"count":6,"bonusPoint":5,"winLimit":6,"maxCount":6},{"startsAt":"2025-07-01T14:33:22.000Z","characterId":122,"count":0,"bonusPoint":0,"winLimit":6,"maxCount":2},{"startsAt":"2025-06-27T16:12:50.000Z","characterId":124,"count":1,"bonusPoint":1,"winLimit":6,"maxCount":8},{"startsAt":"2025-11-28T10:08:18.000Z","characterId":125,"count":1,"bonusPoint":1,"winLimit":6,"maxCount":12},{"startsAt":"2025-11-08T05:41:04.000Z","characterId":126,"count":1,"bonusPoint":1,"winLimit":6,"maxCount":4},{"startsAt":"2025-11-07T11:02:46.000Z","characterId":127,"count":2,"bonusPoint":2,"winLimit":6,"maxCount":8},{"startsAt":"2025-11-09T15:40:08.000Z","characterId":128,"count":4,"bonusPoint":4,"winLimit":6,"maxCount":15},{"startsAt":"2025-11-10T05:58:11.000Z","characterId":129,"count":4,"bonusPoint":4,"winLimit":6,"maxCount":6},{"startsAt":"2025-10-18T02:46:09.000Z","characterId":130,"count":0,"bonusPoint":0,"winLimit":6,"maxCount":8},{"startsAt":"2025-06-06T09:40:10.000Z","characterId":132,"count":2,"bonusPoint":2,"winLimit":6,"maxCount":2},{"startsAt":"2025-11-08T03:19:08.000Z","characterId":133,"count":7,"bonusPoint":5,"winLimit":6,"maxCount":7},{"startsAt":"2025-07-19T08:42:03.000Z","characterId":134,"count":3,"bonusPoint":3,"winLimit":6,"maxCount":12},{"startsAt":"2025-11-08T10:31:08.000Z","characterId":135,"count":3,"bonusPoint":3,"winLimit":6,"maxCount":9},{"startsAt":"2025-07-24T02:13:49.000Z","characterId":136,"count":1,"bonusPoint":1,"winLimit":6,"maxCount":1},{"startsAt":"2025-11-27T01:15:55.000Z","characterId":137,"count":21,"bonusPoint":5,"winLimit":6,"maxCount":89},{"startsAt":"2025-11-09T16:16:38.000Z","characterId":138,"count":2,"bonusPoint":2,"winLimit":6,"maxCount":17},{"startsAt":"2025-10-07T10:24:06.000Z","characterId":139,"count":0,"bonusPoint":0,"winLimit":6,"maxCount":10},{"startsAt":"2025-11-20T08:47:20.000Z","characterId":140,"count":2,"bonusPoint":2,"winLimit":6,"maxCount":5},{"startsAt":"2025-11-07T11:31:15.000Z","characterId":141,"count":3,"bonusPoint":3,"winLimit":6,"maxCount":4},{"startsAt":"2025-11-09T16:01:00.000Z","characterId":142,"count":5,"bonusPoint":5,"winLimit":6,"maxCount":5},{"startsAt":"2025-07-21T08:24:41.000Z","characterId":143,"count":6,"bonusPoint":5,"winLimit":6,"maxCount":6},{"startsAt":"2025-11-08T05:53:55.000Z","characterId":144,"count":5,"bonusPoint":5,"winLimit":6,"maxCount":5},{"startsAt":"2025-07-16T20:55:02.000Z","characterId":145,"count":4,"bonusPoint":4,"winLimit":6,"maxCount":18},{"startsAt":"2025-11-23T14:17:19.000Z","characterId":147,"count":2,"bonusPoint":2,"winLimit":6,"maxCount":26},{"startsAt":"2025-11-28T09:59:33.000Z","characterId":148,"count":1,"bonusPoint":1,"winLimit":6,"maxCount":15}]}}